[{"category":"Abstract-Objects-1","learnable":"wertvoll","normalized":"wertvoll","translation":"قيم, قيمة, قيمًا","partOfSpeech":"Adjective"},{"category":"Accusative-Case","learnable":"buch","normalized":"buch","translation":null,"partOfSpeech":"Neuter Noun"},{"category":"Accusative-Case","learnable":"den","normalized":"den","translation":"أداة تعريف مفعول به ذكر, أداة تعريف مجرور جمع","partOfSpeech":"Masculine Determiner"},{"category":"Accusative-Case","learnable":"die","normalized":"die","translation":"الشرطة, ال (أداة تعريف المؤنث), تلك","partOfSpeech":"Feminine Determiner"},{"category":"Accusative-Case","learnable":"ein","normalized":"ein","translation":"واحد, واحدة, آحادى, أداة تنكير المذكر\/المحايد, إحدى","partOfSpeech":"Neuter Determiner"},{"category":"Accusative-Case","learnable":"einen","normalized":"einen","translation":"واحد, واحدًا, أداة تنكير مفعول به ذكر","partOfSpeech":"Masculine Determiner"},{"category":"Accusative-Case","learnable":"esse","normalized":"esse","translation":"(أنا) آكل","partOfSpeech":"Verb"},{"category":"Accusative-Case","learnable":"essen","normalized":"essen","translation":"(نحن) نأكل, (هم) يأكلون, يأكل, (جمع تكسير) تأكل, (هن) يأكلن, سنأكل, لتناول, لتناول الطعام","partOfSpeech":"Verb"},{"category":"Accusative-Case","learnable":"esst","normalized":"esst","translation":"(أنتم) تأكلون","partOfSpeech":"Verb"},{"category":"Accusative-Case","learnable":"habe","normalized":"habe","translation":"(أنا) عندي","partOfSpeech":"Verb"},{"category":"Accusative-Case","learnable":"haben","normalized":"haben","translation":"(نحن) لدينا, (نحن) عندنا, (هم) عندهم, الحصول, بها, عندها, لديك, لديها, لديهم, لها, معهم, نملك, يملكون","partOfSpeech":"Verb"},{"category":"Accusative-Case","learnable":"habt","normalized":"habt","translation":"(أنتم) عندكم, (أنتم) لديكم","partOfSpeech":"Verb"},{"category":"Accusative-Case","learnable":"hast","normalized":"hast","translation":"(أنت) عندك, (أنت) لديك, معك","partOfSpeech":"Verb"},{"category":"Accusative-Case","learnable":"hat","normalized":"hat","translation":"(هو) عنده\/يملك\/لديه, به, (هي) عندها\/لديها\/تملك, بها, ذات, لدى, لديهم, له, لها, معه, معها","partOfSpeech":"Verb"},{"category":"Accusative-Case","learnable":"isst","normalized":"isst","translation":"(هو) يأكل, (هي) تأكل, (هو) يتناول (طعام)","partOfSpeech":"Verb"},{"category":"Accusative-Case","learnable":"lese","normalized":"lese","translation":"(أنا) أقرأ","partOfSpeech":"Verb"},{"category":"Accusative-Case","learnable":"lesen","normalized":"lesen","translation":"(نحن) نقرأ, يقرأن, (أنت - احترام) تقرأ, يقرؤون","partOfSpeech":"Verb"},{"category":"Accusative-Case","learnable":"liest","normalized":"liest","translation":"(هو) يقرأ, (أنت) تقرأ, (هي) تقرأ","partOfSpeech":"Verb"},{"category":"Accusative-Case","learnable":"milch","normalized":"milch","translation":null,"partOfSpeech":"Feminine Noun"},{"category":"Accusative-Case","learnable":"trinke","normalized":"trinke","translation":"(أنا) أشرب, اشرب (ف. أمر)","partOfSpeech":"Verb"},{"category":"Accusative-Case","learnable":"trinken","normalized":"trinken","translation":"(هم) يشربون, يشربن, (نحن) نشرب, تشرب, تشربن, ونشرب, يشرب, يشربان","partOfSpeech":"Verb"},{"category":"Accusative-Case","learnable":"trinkst","normalized":"trinkst","translation":"(أنت) تشرب, (أنتِ) تشربين","partOfSpeech":"Verb"},{"category":"Accusative-Case","learnable":"zeitung","normalized":"zeitung","translation":null,"partOfSpeech":"Feminine Noun"},{"category":"Accusative-Prepositions","learnable":"durch","normalized":"durch","translation":"خلال, عبر","partOfSpeech":"Preposition"},{"category":"Accusative-Prepositions","learnable":"für","normalized":"fur","translation":"بالنسبة, لأجل, على, ل, لدى, لصالح, مع","partOfSpeech":"Preposition"},{"category":"Accusative-Prepositions","learnable":"gegen","normalized":"gegen","translation":"ضد, عكس","partOfSpeech":"Preposition"},{"category":"Accusative-Prepositions","learnable":"ohne","normalized":"ohne","translation":"بدون, من غير","partOfSpeech":"Preposition"},{"category":"Accusative-Prepositions","learnable":"um","normalized":"um","translation":"حول, فى (الساعة), تقريباً, لكي","partOfSpeech":"Preposition"},{"category":"Accusative-Pronouns","learnable":"dich","normalized":"dich","translation":"لك, عنك, ك, نفسك, ه","partOfSpeech":"Pronoun"},{"category":"Accusative-Pronouns","learnable":"euch","normalized":"euch","translation":"لكم, ـكم","partOfSpeech":"Pronoun"},{"category":"Accusative-Pronouns","learnable":"ihn","normalized":"ihn","translation":"به, إياه, ضمير نصب, ـه","partOfSpeech":"Masculine Pronoun"},{"category":"Accusative-Pronouns","learnable":"mich","normalized":"mich","translation":"لي, نفسي, بى, (ـنـ)ـي, علي, عنى, نفسى","partOfSpeech":"Pronoun"},{"category":"Accusative-Pronouns","learnable":"sie","normalized":"sie","translation":"هي, هى, هم \/ هن, أنها, بها, هؤلاء","partOfSpeech":"Feminine Pronoun"},{"category":"Adjectives:-Accusative","learnable":"detaillierte","normalized":"detaillierte","translation":"المفصلة, مفصلا, مفصلة","partOfSpeech":"Feminine Adjective"},{"category":"Adjectives:-Accusative","learnable":"ehemaligen","normalized":"ehemaligen","translation":"السابق, السابقة, سابقاً","partOfSpeech":"Masculine Adjective"},{"category":"Adjectives:-Accusative","learnable":"eigene","normalized":"eigene","translation":"خاصة, خاص, الخاصة, الخاص","partOfSpeech":"Feminine Adjective"},{"category":"Adjectives:-Accusative","learnable":"einzige","normalized":"einzige","translation":"واحدة, واحد","partOfSpeech":"Feminine Adjective"},{"category":"Adjectives:-Accusative","learnable":"ganzen","normalized":"ganzen","translation":"كاملًا, كامل, كاملةً, بطوله, كله","partOfSpeech":"Masculine Adjective"},{"category":"Adjectives:-Accusative","learnable":"gemeinsame","normalized":"gemeinsame","translation":"مشتركة","partOfSpeech":"Adjective"},{"category":"Adjectives:-Accusative","learnable":"gleiche","normalized":"gleiche","translation":"نفس, نفسها, مساوية","partOfSpeech":"Feminine Adjective"},{"category":"Adjectives:-Accusative","learnable":"hohe","normalized":"hohe","translation":"العالية, العالي, عالية, المرتفعة, عالي","partOfSpeech":"Adjective"},{"category":"Adjectives:-Accusative","learnable":"höhere","normalized":"hohere","translation":"الأطول, الأكبر","partOfSpeech":"Feminine Adjective"},{"category":"Adjectives:-Accusative","learnable":"komplette","normalized":"komplette","translation":"بحاله, كامل","partOfSpeech":"Feminine Adjective"},{"category":"Adjectives:-Accusative","learnable":"kostenlose","normalized":"kostenlose","translation":"المجاني, المجانية, مجاني","partOfSpeech":"Feminine Adjective"},{"category":"Adjectives:-Accusative","learnable":"lange","normalized":"lange","translation":"طويل, طويلة, طويلاً, الطويل, الطويلة","partOfSpeech":"Feminine Adjective"},{"category":"Adjectives:-Accusative","learnable":"langen","normalized":"langen","translation":"طويلة, الطويل, طويلًا, الطويلة, طويل","partOfSpeech":"Masculine Adjective"},{"category":"Adjectives:-Accusative","learnable":"modernen","normalized":"modernen","translation":"العصرية, عصري","partOfSpeech":"Adjective"},{"category":"Adjectives:-Accusative","learnable":"nächsten","normalized":"nachsten","translation":"القادم, التالية, المقبل, التالي","partOfSpeech":"Masculine Adjective"},{"category":"Adjectives:-Accusative","learnable":"neue","normalized":"neue","translation":"جديدة, الجديد, الجدد, الجديدة, جديد, جديدًا, حديد","partOfSpeech":"Neuter Adjective"},{"category":"Adjectives:-Accusative","learnable":"neuen","normalized":"neuen","translation":"الجديدة, جديد, الجدد, الجديد, جديدة, جديدًا","partOfSpeech":"Adjective"},{"category":"Adjectives:-Accusative","learnable":"neues","normalized":"neues","translation":"جديدة, الجديدة, جديد, جديد (غير عاقل), جديدًا","partOfSpeech":"Neuter Adjective"},{"category":"Adjectives:-Accusative","learnable":"offenen","normalized":"offenen","translation":"المفتوحة, مفتوح","partOfSpeech":"Adjective"},{"category":"Adjectives:-Accusative","learnable":"persönlichen","normalized":"personlichen","translation":"شخصية, شخصي, الشخصي","partOfSpeech":"Masculine Adjective"},{"category":"Adjectives:-Accusative","learnable":"technischen","normalized":"technischen","translation":"التقنية, تقنية","partOfSpeech":"Adjective"},{"category":"Adjectives:-Accusative","learnable":"verfügbaren","normalized":"verfugbaren","translation":"المتاحة, المتاحين, متاح","partOfSpeech":"Adjective"},{"category":"Adjectives:-Accusative","learnable":"vergangenen","normalized":"vergangenen","translation":"الماضية, ماضية","partOfSpeech":"Adjective"},{"category":"Adjectives:-Accusative","learnable":"verschiedene","normalized":"verschiedene","translation":"مختلفة, مختلفان","partOfSpeech":"Adjective"},{"category":"Adjectives:-Accusative","learnable":"verschiedenen","normalized":"verschiedenen","translation":"المختلفة, مختلفة, مختلفين (مجرور)","partOfSpeech":"Adjective"},{"category":"Adjectives:-Accusative","learnable":"weitere","normalized":"weitere","translation":"آخر, أوسع, أخرى, إضافية, مزيد","partOfSpeech":"Feminine Adjective"},{"category":"Adjectives:-Accusative","learnable":"weiteres","normalized":"weiteres","translation":"إضافياً, إضافي, آخر","partOfSpeech":"Neuter Adjective"},{"category":"Adjectives:-Accusative","learnable":"zuständigen","normalized":"zustandigen","translation":"المسئول, المسؤول, المسئولون, مسئولين","partOfSpeech":"Masculine Adjective"},{"category":"Adjectives:-Accusative","learnable":"zweite","normalized":"zweite","translation":"ثانية, ثانى","partOfSpeech":"Neuter Adjective"},{"category":"Adjectives:-Dative","learnable":"alten","normalized":"alten","translation":"القدماء, قدماء, كبار السن","partOfSpeech":"Adjective"},{"category":"Adjectives:-Dative","learnable":"bekannten","normalized":"bekannten","translation":"المعروف, معروف, معروفين, مشهور","partOfSpeech":"Feminine Adjective"},{"category":"Adjectives:-Dative","learnable":"deutschen","normalized":"deutschen","translation":"الألماني, ألمانية, الألمان","partOfSpeech":"Adjective"},{"category":"Adjectives:-Dative","learnable":"eigenen","normalized":"eigenen","translation":"الخاص, الخاصة, الخاص به","partOfSpeech":"Feminine Adjective"},{"category":"Adjectives:-Dative","learnable":"gesamten","normalized":"gesamten","translation":"جميع, أكمل, كامل","partOfSpeech":"Neuter Adjective"},{"category":"Adjectives:-Dative","learnable":"heutigen","normalized":"heutigen","translation":"الحاضر, في الوقت الحاضر, حالياً","partOfSpeech":"Feminine Adjective"},{"category":"Adjectives:-Dative","learnable":"privaten","normalized":"privaten","translation":"الخاصة, خاصين, خاص, الخاص","partOfSpeech":"Adjective"},{"category":"Adjectives:-Dative","learnable":"zweiten","normalized":"zweiten","translation":"الثاني","partOfSpeech":"Masculine Adjective"},{"category":"Adjectives:-Nominative-1","learnable":"aktuelle","normalized":"aktuelle","translation":"الحالي, الحالية, حالى, حالية","partOfSpeech":"Feminine Adjective"},{"category":"Adjectives:-Nominative-1","learnable":"alte","normalized":"alte","translation":"القديمة, القديم, العجوز, السابقة, سابقة, قديم (بعد أداة التعريف), قديمة","partOfSpeech":"Feminine Adjective"},{"category":"Adjectives:-Nominative-1","learnable":"besonderen","normalized":"besonderen","translation":"المميزون, مميزون","partOfSpeech":"Adjective"},{"category":"Adjectives:-Nominative-1","learnable":"eigener","normalized":"eigener","translation":"الخاص, الخاص بى","partOfSpeech":"Masculine Adjective"},{"category":"Adjectives:-Nominative-1","learnable":"einzelnen","normalized":"einzelnen","translation":"المنفردة, المفردة","partOfSpeech":"Adjective"},{"category":"Adjectives:-Nominative-1","learnable":"gesamte","normalized":"gesamte","translation":"كل ال..., كامل, كلى, كلية","partOfSpeech":"Masculine Adjective"},{"category":"Adjectives:-Nominative-1","learnable":"größte","normalized":"grosste","translation":"أكبر, اﻷكبر, كبرى","partOfSpeech":"Feminine Adjective"},{"category":"Adjectives:-Nominative-1","learnable":"größten","normalized":"grossten","translation":"أكبر, اﻷكبر","partOfSpeech":"Adjective"},{"category":"Adjectives:-Nominative-1","learnable":"hohen","normalized":"hohen","translation":"العالية, عالي, مرتفعة","partOfSpeech":"Adjective"},{"category":"Adjectives:-Nominative-1","learnable":"hoher","normalized":"hoher","translation":"أعلى","partOfSpeech":"Masculine Adjective"},{"category":"Adjectives:-Nominative-1","learnable":"höheren","normalized":"hoheren","translation":"أعلى","partOfSpeech":"Adjective"},{"category":"Adjectives:-Nominative-1","learnable":"individuellen","normalized":"individuellen","translation":"فردية","partOfSpeech":"Adjective"},{"category":"Adjectives:-Nominative-1","learnable":"internationale","normalized":"internationale","translation":"الدولية, العالمي, دولي, عالمي","partOfSpeech":"Feminine Adjective"},{"category":"Adjectives:-Nominative-1","learnable":"internationalen","normalized":"internationalen","translation":"الدولية, الدوليون, دولي","partOfSpeech":"Adjective"},{"category":"Adjectives:-Nominative-1","learnable":"jugendliche","normalized":"jugendliche","translation":"الشابة, شابة","partOfSpeech":"Feminine Adjective"},{"category":"Adjectives:-Nominative-1","learnable":"letzter","normalized":"letzter","translation":"اﻷخير, الأخيرة, أخيرة","partOfSpeech":"Masculine Adjective"},{"category":"Adjectives:-Nominative-1","learnable":"linken","normalized":"linken","translation":"اليسارية, الأيسر","partOfSpeech":"Adjective"},{"category":"Adjectives:-Nominative-1","learnable":"müde","normalized":"mude","translation":"مرهق, متعب, مرهقون, تعبان, متعباً, مرهقة","partOfSpeech":"Feminine Adjective"},{"category":"Adjectives:-Nominative-1","learnable":"nächster","normalized":"nachster","translation":"القادم","partOfSpeech":"Masculine Adjective"},{"category":"Adjectives:-Nominative-1","learnable":"normalen","normalized":"normalen","translation":"العادية, عادي, عادية, طبيعي, طبيعية","partOfSpeech":"Adjective"},{"category":"Adjectives:-Nominative-1","learnable":"notwendigen","normalized":"notwendigen","translation":"الضرورية, الضروريين, ضرورية","partOfSpeech":"Adjective"},{"category":"Adjectives:-Nominative-1","learnable":"öffentliche","normalized":"offentliche","translation":"عامة","partOfSpeech":"Feminine Adjective"},{"category":"Adjectives:-Nominative-1","learnable":"öffentlichen","normalized":"offentlichen","translation":"عام","partOfSpeech":"Adjective"},{"category":"Adjectives:-Nominative-1","learnable":"passende","normalized":"passende","translation":"المناسبة, المناسب, مناسبة, مناسب","partOfSpeech":"Feminine Adjective"},{"category":"Adjectives:-Nominative-1","learnable":"passenden","normalized":"passenden","translation":"مناسبة, مناسب","partOfSpeech":"Adjective"},{"category":"Adjectives:-Nominative-1","learnable":"private","normalized":"private","translation":"خاصة","partOfSpeech":"Adjective"},{"category":"Adjectives:-Nominative-1","learnable":"richtige","normalized":"richtige","translation":"صحيحة","partOfSpeech":"Feminine Adjective"},{"category":"Adjectives:-Nominative-1","learnable":"speziellen","normalized":"speziellen","translation":"الخاصة, خاصة","partOfSpeech":"Adjective"},{"category":"Adjectives:-Nominative-1","learnable":"übrigen","normalized":"ubrigen","translation":"بقية","partOfSpeech":"Adjective"},{"category":"Adjectives:-Nominative-1","learnable":"weiterer","normalized":"weiterer","translation":"آخر, إضافي","partOfSpeech":"Masculine Adjective"},{"category":"Adjectives:-Nominative-1","learnable":"wichtigen","normalized":"wichtigen","translation":"مهمون","partOfSpeech":"Adjective"},{"category":"Adjectives:-Nominative-1","learnable":"wichtigsten","normalized":"wichtigsten","translation":"الأهم, المهم","partOfSpeech":"Adjective"},{"category":"Adjectives:-Nominative-1","learnable":"zufälliger","normalized":"zufalliger","translation":"بالصدفة, مصادفة, صادفة","partOfSpeech":"Masculine Adjective"},{"category":"Adjectives:-Nominative-1","learnable":"zusätzliche","normalized":"zusatzliche","translation":"إضافي, الإضافية, زائد, إضافية, زائدة","partOfSpeech":"Feminine Adjective"},{"category":"Adjectives:-Nominative-2","learnable":"ähnlichen","normalized":"ahnlichen","translation":"المتشابهة, المتشابهان, مشابه","partOfSpeech":"Adjective"},{"category":"Adjectives:-Nominative-2","learnable":"aktive","normalized":"aktive","translation":"النشط, نشطان, نشطاء, نشط, نشيط","partOfSpeech":"Masculine Adjective"},{"category":"Adjectives:-Nominative-2","learnable":"ehemalige","normalized":"ehemalige","translation":"سابقون","partOfSpeech":"Masculine Adjective"},{"category":"Adjectives:-Nominative-2","learnable":"eigenes","normalized":"eigenes","translation":"الخاصة","partOfSpeech":"Neuter Adjective"},{"category":"Adjectives:-Nominative-2","learnable":"einfache","normalized":"einfache","translation":"بسيطة, بسيط","partOfSpeech":"Neuter Adjective"},{"category":"Adjectives:-Nominative-2","learnable":"einfachen","normalized":"einfachen","translation":"البسيطة, بسيطة, السهلة, سهلة","partOfSpeech":"Adjective"},{"category":"Adjectives:-Nominative-2","learnable":"externe","normalized":"externe","translation":"الخارج, خارجى \/ من جهة خارجية","partOfSpeech":"Masculine Adjective"},{"category":"Adjectives:-Nominative-2","learnable":"freien","normalized":"freien","translation":"الحرة, الأحرار, الفارغة, حرة, فارغ","partOfSpeech":"Adjective"},{"category":"Adjectives:-Nominative-2","learnable":"gelber","normalized":"gelber","translation":"صفراء, الصفراء","partOfSpeech":"Masculine Adjective"},{"category":"Adjectives:-Nominative-2","learnable":"gleichen","normalized":"gleichen","translation":"نفس","partOfSpeech":"Adjective"},{"category":"Adjectives:-Nominative-2","learnable":"günstige","normalized":"gunstige","translation":"رخيصة","partOfSpeech":"Adjective"},{"category":"Adjectives:-Nominative-2","learnable":"höchste","normalized":"hochste","translation":"أعلى, أطول","partOfSpeech":"Masculine Adjective"},{"category":"Adjectives:-Nominative-2","learnable":"individuelle","normalized":"individuelle","translation":"الفردية, فردى, الفردي, شخصى","partOfSpeech":"Feminine Adjective"},{"category":"Adjectives:-Nominative-2","learnable":"interessante","normalized":"interessante","translation":"مشوقة, مثير, شيّق, مثيرة","partOfSpeech":"Adjective"},{"category":"Adjectives:-Nominative-2","learnable":"jungen","normalized":"jungen","translation":"الصغيرة, صغير, صغيرة","partOfSpeech":"Adjective"},{"category":"Adjectives:-Nominative-2","learnable":"letzten","normalized":"letzten","translation":"الأخيرة, الماضي, أخيرة (جمع بعد die)","partOfSpeech":"Adjective"},{"category":"Adjectives:-Nominative-2","learnable":"möglichen","normalized":"moglichen","translation":"المحتملة, محتمل","partOfSpeech":"Adjective"},{"category":"Adjectives:-Nominative-2","learnable":"nächste","normalized":"nachste","translation":"تالية","partOfSpeech":"Feminine Adjective"},{"category":"Adjectives:-Nominative-2","learnable":"neuesten","normalized":"neuesten","translation":"أجدد, الأجدد","partOfSpeech":"Adjective"},{"category":"Adjectives:-Nominative-2","learnable":"offene","normalized":"offene","translation":"مفتوحة, مفتوح, المفتوح","partOfSpeech":"Feminine Adjective"},{"category":"Adjectives:-Nominative-2","learnable":"öffentliches","normalized":"offentliches","translation":"عمومي, مفتوح","partOfSpeech":"Neuter Adjective"},{"category":"Adjectives:-Nominative-2","learnable":"persönliche","normalized":"personliche","translation":"الشخصية, شخصية, الشخصي, شخصي","partOfSpeech":"Masculine Adjective"},{"category":"Adjectives:-Nominative-2","learnable":"politischen","normalized":"politischen","translation":"سياسية","partOfSpeech":"Adjective"},{"category":"Adjectives:-Nominative-2","learnable":"schöne","normalized":"schone","translation":"جميلة, جميل","partOfSpeech":"Feminine Adjective"},{"category":"Adjectives:-Nominative-2","learnable":"schönen","normalized":"schonen","translation":"الجميلة, الجميلتان, جميلة","partOfSpeech":"Adjective"},{"category":"Adjectives:-Nominative-2","learnable":"soziale","normalized":"soziale","translation":"اجتماعي, اجتماعى, اجتماعية","partOfSpeech":"Neuter Adjective"},{"category":"Adjectives:-Nominative-2","learnable":"sozialen","normalized":"sozialen","translation":"اجتماعية","partOfSpeech":"Adjective"},{"category":"Adjectives:-Nominative-2","learnable":"soziales","normalized":"soziales","translation":"اجتماعي","partOfSpeech":"Neuter Adjective"},{"category":"Adjectives:-Nominative-2","learnable":"starke","normalized":"starke","translation":"أقوياء, قوية","partOfSpeech":"Adjective"},{"category":"Adjectives:-Nominative-2","learnable":"starken","normalized":"starken","translation":"الأقوياء, قوية, أقوياء, القويات, قوى (منصوب)","partOfSpeech":"Adjective"},{"category":"Adjectives:-Nominative-2","learnable":"unterschiedliche","normalized":"unterschiedliche","translation":"مختلفة, مختلفون, مختلفان, متباينون, مختلف \/ متابين","partOfSpeech":"Adjective"},{"category":"Adjectives:-Nominative-2","learnable":"wichtige","normalized":"wichtige","translation":"مهم, المهمة, مهمة, مهمون, مهمين","partOfSpeech":"Adjective"},{"category":"Adjectives:-Nominative-2","learnable":"zusätzlichen","normalized":"zusatzlichen","translation":"الإضافية, إضافية, زائد","partOfSpeech":"Adjective"},{"category":"Adjectives:-Predicative","learnable":"frei","normalized":"frei","translation":"حر, شاغرة, أحرار, الحرة, حرة, خالي, فارغ, متفرغ","partOfSpeech":"Adjective"},{"category":"Adjectives:-Predicative","learnable":"groß","normalized":"gross","translation":"كبيرة, كبير, كبير (حجماً), بكبير, طول, طويل, كبار","partOfSpeech":"Adjective"},{"category":"Adjectives:-Predicative","learnable":"klar","normalized":"klar","translation":"واضح, صافي, واضحاً, تمام, جاهز, صافٍ, مفهوم","partOfSpeech":"Adjective"},{"category":"Adjectives:-Predicative","learnable":"klein","normalized":"klein","translation":"صغيرة, صغير, صغار, صغيراً, صغيرًا","partOfSpeech":"Adjective"},{"category":"Adjectives:-Predicative","learnable":"lang","normalized":"lang","translation":"طويل, طويلة, الطويل, الطويلة","partOfSpeech":"Adjective"},{"category":"Adjectives:-Predicative","learnable":"laut","normalized":"laut","translation":"صاخب, صاخبة, صاخبون","partOfSpeech":"Adjective"},{"category":"Adjectives:-Predicative","learnable":"leicht","normalized":"leicht","translation":"خفيفة, خفيف, بسهولة, سهلاً, سهلة","partOfSpeech":"Adjective"},{"category":"Adjectives:-Predicative","learnable":"leise","normalized":"leise","translation":"هادئ, هادئون, هادئة, هادئين","partOfSpeech":"Adjective"},{"category":"Adjectives:-Predicative","learnable":"normal","normalized":"normal","translation":"طبيعي, عادية, عادى, طبيعية, عادي, عادياً, عاديون, عاديًا","partOfSpeech":"Adjective"},{"category":"Adjectives:-Predicative","learnable":"perfekt","normalized":"perfekt","translation":"مثالي, مثالية, بإتقان, بطريقة كاملة, بطريقة مثالية, كامل, مثاليًا, هم) مثاليون)","partOfSpeech":"Adjective"},{"category":"Adjectives:-Predicative","learnable":"ruhig","normalized":"ruhig","translation":"ساكنون, هادئة, هادئ, ساكن, ساكنان, ساكنة, صامت, صامتة, صامتون, هادئون","partOfSpeech":"Adjective"},{"category":"Adjectives:-Predicative","learnable":"rund","normalized":"rund","translation":"مدورة, مستدير, مستديرة, على ما يرام, مدور","partOfSpeech":"Adjective"},{"category":"Adjectives:-Predicative","learnable":"schlecht","normalized":"schlecht","translation":"سيئة, سيئ, بشكل سيئ, سيءً, سيئاً, سيّء, ضارة","partOfSpeech":"Adjective"},{"category":"Adjectives:-Predicative","learnable":"schwach","normalized":"schwach","translation":"ضعيف, ضعيفة, ضعفاء, ضعيفاً","partOfSpeech":"Adjective"},{"category":"Adjectives:-Predicative","learnable":"toll","normalized":"toll","translation":"رائع, رائعة, رائعون, رائعتان, عظيم","partOfSpeech":"Adjective"},{"category":"Adjectives:-Predicative-2","learnable":"aktiv","normalized":"aktiv","translation":"نشيط, نشط, نشطة, النشط, نشطاء, نشطان","partOfSpeech":"Adjective"},{"category":"Adjectives:-Predicative-2","learnable":"allgemein","normalized":"allgemein","translation":"عام, عامةً, شامل","partOfSpeech":"Adjective"},{"category":"Adjectives:-Predicative-2","learnable":"ausgezeichnet","normalized":"ausgezeichnet","translation":"ممتاز, ممتازة","partOfSpeech":"Adjective"},{"category":"Adjectives:-Predicative-2","learnable":"automatisch","normalized":"automatisch","translation":"تلقائي, أوتوماتيكيّ, أوتوماتيكيّون","partOfSpeech":"Adjective"},{"category":"Adjectives:-Predicative-2","learnable":"beliebt","normalized":"beliebt","translation":"محبوبة, محبوب, محبوبون, محبوباً, مشهور","partOfSpeech":"Adjective"},{"category":"Adjectives:-Predicative-2","learnable":"bereit","normalized":"bereit","translation":"مستعد, جاهز, مستعدون","partOfSpeech":"Adjective"},{"category":"Adjectives:-Predicative-2","learnable":"echt","normalized":"echt","translation":"حقيقي, حقيقية, حقيقيون, حقيقى","partOfSpeech":"Adjective"},{"category":"Adjectives:-Predicative-2","learnable":"egal","normalized":"egal","translation":"متساوٍ","partOfSpeech":"Adjective"},{"category":"Adjectives:-Predicative-2","learnable":"extrem","normalized":"extrem","translation":"للغاية","partOfSpeech":"Adjective"},{"category":"Adjectives:-Predicative-2","learnable":"falsch","normalized":"falsch","translation":"خطأ, خاطئة, خاطئاً","partOfSpeech":"Adjective"},{"category":"Adjectives:-Predicative-2","learnable":"fest","normalized":"fest","translation":"محكم, محكمة","partOfSpeech":"Adjective"},{"category":"Adjectives:-Predicative-2","learnable":"fit","normalized":"fit","translation":"لائق, لائق (رياضياً)","partOfSpeech":"Adjective"},{"category":"Adjectives:-Predicative-2","learnable":"gemeinsam","normalized":"gemeinsam","translation":"سويًا, معًا","partOfSpeech":"Adjective"},{"category":"Adjectives:-Predicative-2","learnable":"hart","normalized":"hart","translation":"صلبة, صلب","partOfSpeech":"Adjective"},{"category":"Adjectives:-Predicative-2","learnable":"hilfreich","normalized":"hilfreich","translation":"مفيد, مفيدة, مفيدًا, مفيدان, نافع","partOfSpeech":"Adjective"},{"category":"Adjectives:-Predicative-2","learnable":"kaputt","normalized":"kaputt","translation":"معطل, معطلة, مكسور, مكسورة","partOfSpeech":"Adjective"},{"category":"Adjectives:-Predicative-2","learnable":"knapp","normalized":"knapp","translation":"محدودة, محدود","partOfSpeech":"Adjective"},{"category":"Adjectives:-Predicative-2","learnable":"komisch","normalized":"komisch","translation":"غريب, مضحك","partOfSpeech":"Adjective"},{"category":"Adjectives:-Predicative-2","learnable":"komplett","normalized":"komplett","translation":"مكتمل, بالكامل, تمامًا, بحالها, تماماً, كامل, كاملاً, مكتملة","partOfSpeech":"Adjective"},{"category":"Adjectives:-Predicative-2","learnable":"offen","normalized":"offen","translation":"مفتوح, مفتوحة, غير محدد, منفتح على","partOfSpeech":"Adjective"},{"category":"Adjectives:-Predicative-2","learnable":"original","normalized":"original","translation":"أصلي, أصلية","partOfSpeech":"Adjective"},{"category":"Adjectives:-Predicative-2","learnable":"plötzlich","normalized":"plotzlich","translation":"فجأة, مفاجئ","partOfSpeech":"Adjective"},{"category":"Adjectives:-Predicative-2","learnable":"privat","normalized":"privat","translation":"خاصة, خصوصي, خاص, في خصوصية","partOfSpeech":"Adjective"},{"category":"Adjectives:-Predicative-2","learnable":"regional","normalized":"regional","translation":"محلية, محلي","partOfSpeech":"Adjective"},{"category":"Adjectives:-Predicative-2","learnable":"relativ","normalized":"relativ","translation":"نسبياً, نسبي, نسبيًا","partOfSpeech":"Adjective"},{"category":"Adjectives:-Predicative-2","learnable":"seltsam","normalized":"seltsam","translation":"غريب, غريبة","partOfSpeech":"Adjective"},{"category":"Adjectives:-Predicative-2","learnable":"sinnvoll","normalized":"sinnvoll","translation":"معقول, معقولة, سديد","partOfSpeech":"Adjective"},{"category":"Adjectives:-Predicative-2","learnable":"tatsächlich","normalized":"tatsachlich","translation":"بالفعل","partOfSpeech":"Adjective"},{"category":"Adjectives:-Predicative-2","learnable":"verantwortlich","normalized":"verantwortlich","translation":"مسئول عن, المسئول, المسؤولة, مسؤول","partOfSpeech":"Adjective"},{"category":"Adjectives:-Predicative-2","learnable":"weich","normalized":"weich","translation":"لينة, لين, طرية","partOfSpeech":"Adjective"},{"category":"Adjectives:-Predicative-2","learnable":"wert","normalized":"wert","translation":"قيم, يساوي, قيمًا","partOfSpeech":"Adjective"},{"category":"Adjectives:-Predicative-2","learnable":"zuständig","normalized":"zustandig","translation":"مسئولون, المسئولة, المسؤول, المسئول, مسؤول, مسئولة","partOfSpeech":"Adjective"},{"category":"Adjectives:-Predicative-3","learnable":"abhängig","normalized":"abhangig","translation":"غير مستقل","partOfSpeech":"Adjective"},{"category":"Adjectives:-Predicative-3","learnable":"begeistert","normalized":"begeistert","translation":"متحمس, متحمسون","partOfSpeech":"Adjective"},{"category":"Adjectives:-Predicative-3","learnable":"bekannt","normalized":"bekannt","translation":"مشهور, مشهورة, معروف, معروفة","partOfSpeech":"Adjective"},{"category":"Adjectives:-Predicative-3","learnable":"deutlich","normalized":"deutlich","translation":"بوضوح, واضح, معقول","partOfSpeech":"Adjective"},{"category":"Adjectives:-Predicative-3","learnable":"eindeutig","normalized":"eindeutig","translation":"واضحة, الواضح, واضح","partOfSpeech":"Adjective"},{"category":"Adjectives:-Predicative-3","learnable":"individuell","normalized":"individuell","translation":"فردي, فرديون, الفردي, الفردية","partOfSpeech":"Adjective"},{"category":"Adjectives:-Predicative-3","learnable":"international","normalized":"international","translation":"عالمى, عالمي, دولية, عالمية","partOfSpeech":"Adjective"},{"category":"Adjectives:-Predicative-3","learnable":"kostenlos","normalized":"kostenlos","translation":"مجانية, بالمجان, مجاني, مجانى","partOfSpeech":"Adjective"},{"category":"Adjectives:-Predicative-3","learnable":"möglich","normalized":"moglich","translation":"ممكن, ممكنًا, ممكنة, الممكن","partOfSpeech":"Adjective"},{"category":"Adjectives:-Predicative-3","learnable":"notwendig","normalized":"notwendig","translation":"ضروري, ضرورية, ضروريون","partOfSpeech":"Adjective"},{"category":"Adjectives:-Predicative-3","learnable":"nützlich","normalized":"nutzlich","translation":"مفيد, مفيدة, مفيدًا","partOfSpeech":"Adjective"},{"category":"Adjectives:-Predicative-3","learnable":"persönlich","normalized":"personlich","translation":"شخصية, شخصي, شخصى, الشخصي","partOfSpeech":"Adjective"},{"category":"Adjectives:-Predicative-3","learnable":"positiv","normalized":"positiv","translation":"إيجابي, إيجابى, إيجابية, إجابية, إيجابين","partOfSpeech":"Adjective"},{"category":"Adjectives:-Predicative-3","learnable":"praktisch","normalized":"praktisch","translation":"عملي, عملية, عمليًا","partOfSpeech":"Adjective"},{"category":"Adjectives:-Predicative-3","learnable":"selbstverständlich","normalized":"selbstverstandlich","translation":"بديهي, البديهي","partOfSpeech":"Adjective"},{"category":"Adjectives:-Predicative-3","learnable":"sichtbar","normalized":"sichtbar","translation":"ظاهر, ظاهرة, واضحة, مرئي, مرئية, واضح","partOfSpeech":"Adjective"},{"category":"Adjectives:-Predicative-3","learnable":"unabhängig","normalized":"unabhangig","translation":"مستقلة, مستقل, بدون تحيز","partOfSpeech":"Adjective"},{"category":"Adjectives:-Predicative-3","learnable":"unbekannt","normalized":"unbekannt","translation":"غير معروفة, غير معروف, مجهولة","partOfSpeech":"Adjective"},{"category":"Adjectives:-Predicative-3","learnable":"unmöglich","normalized":"unmoglich","translation":"مستحيل","partOfSpeech":"Adjective"},{"category":"Adjectives:-Predicative-3","learnable":"unsichtbar","normalized":"unsichtbar","translation":"خفي, غير مرئي","partOfSpeech":"Adjective"},{"category":"Adjectives:-Predicative-3","learnable":"verfügbar","normalized":"verfugbar","translation":"متاح, متاحة, متاحين, المتاحة, متاحًا","partOfSpeech":"Adjective"},{"category":"Adjectives:-Predicative-3","learnable":"verpflichtet","normalized":"verpflichtet","translation":"ملزم, مُلزم","partOfSpeech":"Adjective"},{"category":"Adjectives:-Predicative-3","learnable":"wahrscheinlich","normalized":"wahrscheinlich","translation":"على الأرجح","partOfSpeech":"Adjective"},{"category":"Adjectives:-Predicative-3","learnable":"zufrieden","normalized":"zufrieden","translation":"راضي, راضون, راضية, راض ٍ, راضيًا, راضٍ","partOfSpeech":"Adjective"},{"category":"Adverbs-1","learnable":"alleine","normalized":"alleine","translation":"وحدي, وحدها, بمفردها, بمفردي, لوحدها, وحده, وحيداً, وحيدٌ","partOfSpeech":"Adverb"},{"category":"Adverbs-1","learnable":"auch","normalized":"auch","translation":"أيضاً, كذلك","partOfSpeech":"Adverb"},{"category":"Adverbs-1","learnable":"dran","normalized":"dran","translation":null,"partOfSpeech":"Adverb"},{"category":"Adverbs-1","learnable":"gern","normalized":"gern","translation":"بكل سرور, بسرور, تحب","partOfSpeech":"Adverb"},{"category":"Adverbs-1","learnable":"gerne","normalized":"gerne","translation":"أود, أحب, بسرور, يحب","partOfSpeech":"Adverb"},{"category":"Adverbs-1","learnable":"immer","normalized":"immer","translation":"دائمًا, دائماً, دائما","partOfSpeech":"Adverb"},{"category":"Adverbs-1","learnable":"noch","normalized":"noch","translation":"مازال, مازالت, لا زال, حتى الان, غير ذلك, لازال, مازلت","partOfSpeech":"Adverb"},{"category":"Adverbs-1","learnable":"nur","normalized":"nur","translation":"فقط, مجرد","partOfSpeech":"Adverb"},{"category":"Adverbs-1","learnable":"schon","normalized":"schon","translation":"بالفعل, قد","partOfSpeech":"Adverb"},{"category":"Adverbs-1","learnable":"so","normalized":"so","translation":"كذلك, هكذا, كم, جداً, جدًا, كم ... !","partOfSpeech":"Adverb"},{"category":"Adverbs-1","learnable":"vielleicht","normalized":"vielleicht","translation":"ربما, قد تكون","partOfSpeech":"Adverb"},{"category":"Adverbs-1","learnable":"wieder","normalized":"wieder","translation":"مجدداً, من جديد","partOfSpeech":"Adverb"},{"category":"Adverbs-1","learnable":"wirklich","normalized":"wirklich","translation":"فعلاً, بالفعل, حقاً","partOfSpeech":"Adjective"},{"category":"Adverbs-1","learnable":"zusammen","normalized":"zusammen","translation":"سويًا, سوياً, سويا, مع بعض, معًا","partOfSpeech":"Adverb"},{"category":"Adverbs-2","learnable":"allein","normalized":"allein","translation":"بمفرده, وحيد, بمفردى, بمفردي, وحيدًا","partOfSpeech":"Adverb"},{"category":"Adverbs-2","learnable":"außerdem","normalized":"ausserdem","translation":"بالإضافة إلى ذلك, أيضاً","partOfSpeech":"Adverb"},{"category":"Adverbs-2","learnable":"bereits","normalized":"bereits","translation":"بالفعل","partOfSpeech":"Adverb"},{"category":"Adverbs-2","learnable":"besonders","normalized":"besonders","translation":"بشكلٍ خاص, مميز, بالأخص, جداً, خصوصًا","partOfSpeech":"Adverb"},{"category":"Adverbs-2","learnable":"dabei","normalized":"dabei","translation":"في ذلك, معه","partOfSpeech":"Adverb"},{"category":"Adverbs-2","learnable":"daher","normalized":"daher","translation":"لذلك","partOfSpeech":"Adverb"},{"category":"Adverbs-2","learnable":"damit","normalized":"damit","translation":"من ذلك, كي","partOfSpeech":"Adverb"},{"category":"Adverbs-2","learnable":"darüber","normalized":"daruber","translation":"ذلك, عن ذلك, على ذلك, بذلك","partOfSpeech":"Adverb"},{"category":"Adverbs-2","learnable":"dazu","normalized":"dazu","translation":"لذلك, ذلك","partOfSpeech":"Adverb"},{"category":"Adverbs-2","learnable":"durchaus","normalized":"durchaus","translation":"بالتأكيد","partOfSpeech":"Adverb"},{"category":"Adverbs-2","learnable":"einmal","normalized":"einmal","translation":"مرة, مرة واحدة","partOfSpeech":"Adverb"},{"category":"Adverbs-2","learnable":"erneut","normalized":"erneut","translation":"من جديد","partOfSpeech":"Adjective"},{"category":"Adverbs-2","learnable":"genauso","normalized":"genauso","translation":"تماماً, تمامًا","partOfSpeech":"Adverb"},{"category":"Adverbs-2","learnable":"jedenfalls","normalized":"jedenfalls","translation":"على أية حال","partOfSpeech":"Adverb"},{"category":"Adverbs-2","learnable":"jedoch","normalized":"jedoch","translation":"لكن","partOfSpeech":"Adverb"},{"category":"Adverbs-2","learnable":"kaum","normalized":"kaum","translation":"بالكاد","partOfSpeech":"Adverb"},{"category":"Adverbs-2","learnable":"meistens","normalized":"meistens","translation":"غالباً, غالبًا","partOfSpeech":"Adverb"},{"category":"Adverbs-2","learnable":"mindestens","normalized":"mindestens","translation":"على الأقل","partOfSpeech":"Adverb"},{"category":"Adverbs-2","learnable":"nun","normalized":"nun","translation":"الآن","partOfSpeech":"Adverb"},{"category":"Adverbs-2","learnable":"selber","normalized":"selber","translation":"بنفسك, نفسي, نفسكم, بنفسها","partOfSpeech":"Adverb"},{"category":"Adverbs-2","learnable":"selbst","normalized":"selbst","translation":"بنفسي, بأنفسهم, بنفسنا, نفسها","partOfSpeech":"Adverb"},{"category":"Adverbs-2","learnable":"sonst","normalized":"sonst","translation":"عدا عن ذلك","partOfSpeech":"Adverb"},{"category":"Adverbs-2","learnable":"sowohl","normalized":"sowohl","translation":null,"partOfSpeech":"Conjunction"},{"category":"Adverbs-2","learnable":"überhaupt","normalized":"uberhaupt","translation":"على الإطلاق","partOfSpeech":"Adverb"},{"category":"Adverbs-2","learnable":"völlig","normalized":"vollig","translation":"بالكامل, تماماً","partOfSpeech":"Adjective"},{"category":"Adverbs-2","learnable":"weder","normalized":"weder","translation":null,"partOfSpeech":"Conjunction"},{"category":"Adverbs-2","learnable":"zuerst","normalized":"zuerst","translation":"أولاً","partOfSpeech":"Adverb"},{"category":"Adverbs-2","learnable":"zuletzt","normalized":"zuletzt","translation":"أخيراً","partOfSpeech":"Adverb"},{"category":"Adverbs-3","learnable":"allerdings","normalized":"allerdings","translation":"شك, بالطبع","partOfSpeech":"Adverb"},{"category":"Adverbs-3","learnable":"also","normalized":"also","translation":"إذًا","partOfSpeech":"Adverb"},{"category":"Adverbs-3","learnable":"anders","normalized":"anders","translation":"مختلف, مختلفًا, بشكل آخر","partOfSpeech":"Adverb"},{"category":"Adverbs-3","learnable":"ansonsten","normalized":"ansonsten","translation":"فيما عدا ذلك","partOfSpeech":"Adverb"},{"category":"Adverbs-3","learnable":"bisher","normalized":"bisher","translation":"حتى الآن","partOfSpeech":"Adverb"},{"category":"Adverbs-3","learnable":"dadurch","normalized":"dadurch","translation":"خلال ذلك","partOfSpeech":"Adverb"},{"category":"Adverbs-3","learnable":"dafür","normalized":"dafur","translation":"على ذلك, لذلك","partOfSpeech":"Adverb"},{"category":"Adverbs-3","learnable":"daran","normalized":"daran","translation":"فى ذلك, في ذلك, على ذلك","partOfSpeech":"Adverb"},{"category":"Adverbs-3","learnable":"darauf","normalized":"darauf","translation":"بذلك, على ذلك","partOfSpeech":"Adverb"},{"category":"Adverbs-3","learnable":"darum","normalized":"darum","translation":"لأجل ذلك","partOfSpeech":"Adverb"},{"category":"Adverbs-3","learnable":"davon","normalized":"davon","translation":"من ذلك, بأن","partOfSpeech":"Adverb"},{"category":"Adverbs-3","learnable":"deshalb","normalized":"deshalb","translation":"لأجل ذلك","partOfSpeech":"Adverb"},{"category":"Adverbs-3","learnable":"drin","normalized":"drin","translation":"داخل ذلك","partOfSpeech":"Adverb"},{"category":"Adverbs-3","learnable":"eigentlich","normalized":"eigentlich","translation":"فى الواقع","partOfSpeech":"Adverb"},{"category":"Adverbs-3","learnable":"herzlich","normalized":"herzlich","translation":"بإخلاص, بصدق","partOfSpeech":"Adjective"},{"category":"Adverbs-3","learnable":"mal","normalized":"mal","translation":"مرة","partOfSpeech":"Adverb"},{"category":"Adverbs-3","learnable":"natürlich","normalized":"naturlich","translation":"بالطبع, طبيعي","partOfSpeech":"Adverb"},{"category":"Adverbs-3","learnable":"sogar","normalized":"sogar","translation":"حتى","partOfSpeech":"Adverb"},{"category":"Adverbs-3","learnable":"soweit","normalized":"soweit","translation":"حتى الآن, إلى ذلك الحد","partOfSpeech":"Adverb"},{"category":"Adverbs-3","learnable":"trotzdem","normalized":"trotzdem","translation":"بالرغم من ذلك","partOfSpeech":"Adverb"},{"category":"Adverbs-3","learnable":"übrigens","normalized":"ubrigens","translation":"بالمناسبة","partOfSpeech":"Adverb"},{"category":"Adverbs-3","learnable":"wenigstens","normalized":"wenigstens","translation":"على الأقل","partOfSpeech":"Adverb"},{"category":"Adverbs-3","learnable":"wohl","normalized":"wohl","translation":"حقًا, بخير","partOfSpeech":"Adverb"},{"category":"Adverbs-3","learnable":"zugleich","normalized":"zugleich","translation":"فى نفس الوقت","partOfSpeech":"Adverb"},{"category":"Adverbs-3","learnable":"zumindest","normalized":"zumindest","translation":"على الأقل","partOfSpeech":"Adverb"},{"category":"Adverbs-4","learnable":"dennoch","normalized":"dennoch","translation":"مع ذلك","partOfSpeech":"Adverb"},{"category":"Adverbs-4","learnable":"derzeit","normalized":"derzeit","translation":"فى الوقت الحالى, حاليًا","partOfSpeech":"Adverb"},{"category":"Adverbs-4","learnable":"deswegen","normalized":"deswegen","translation":null,"partOfSpeech":"Adverb"},{"category":"Adverbs-4","learnable":"ebenfalls","normalized":"ebenfalls","translation":"كذلك","partOfSpeech":"Adverb"},{"category":"Adverbs-4","learnable":"hiermit","normalized":"hiermit","translation":"فى ذلك, فى هذا, بموجب هذه الوثيقة","partOfSpeech":"Adverb"},{"category":"Adverbs-4","learnable":"hierzu","normalized":"hierzu","translation":"بخصوص هذا, إلى هذا, لهذا الأمر, لهذا الغرض","partOfSpeech":"Adverb"},{"category":"Adverbs-4","learnable":"hingegen","normalized":"hingegen","translation":"على العكس","partOfSpeech":"Adverb"},{"category":"Adverbs-4","learnable":"hinzu","normalized":"hinzu","translation":"علاوة على ذلك","partOfSpeech":"Adverb"},{"category":"Adverbs-4","learnable":"insbesondere","normalized":"insbesondere","translation":"خصوصًا, بالأخص","partOfSpeech":"Adverb"},{"category":"Adverbs-4","learnable":"jederzeit","normalized":"jederzeit","translation":"أى وقت, فى كل وقت, كل وقت","partOfSpeech":"Adverb"},{"category":"Adverbs-4","learnable":"mittlerweile","normalized":"mittlerweile","translation":null,"partOfSpeech":"Adverb"},{"category":"Adverbs-4","learnable":"nochmals","normalized":"nochmals","translation":"مرة آخرى, مجددًا","partOfSpeech":"Adverb"},{"category":"Adverbs-4","learnable":"schließlich","normalized":"schliesslich","translation":null,"partOfSpeech":"Adverb"},{"category":"Adverbs-4","learnable":"soeben","normalized":"soeben","translation":"منذ لحظة, فى هذه اللحظة","partOfSpeech":"Adverb"},{"category":"Adverbs-4","learnable":"weiterhin","normalized":"weiterhin","translation":"علاوة على ذلك, من الآن فصاعدًا, فى المستقبل","partOfSpeech":"Adverb"},{"category":"Animals-1","learnable":"schwein","normalized":"schwein","translation":null,"partOfSpeech":"Neuter Noun"},{"category":"Animals-2","learnable":"gefährlich","normalized":"gefahrlich","translation":"خطير, خطيرة","partOfSpeech":"Adjective"},{"category":"Animals-2","learnable":"harmlos","normalized":"harmlos","translation":"غير مؤذية, غير مؤذى","partOfSpeech":"Adjective"},{"category":"Animals-2","learnable":"verrückt","normalized":"verruckt","translation":"مجانين, مجنون, مجنونا","partOfSpeech":"Adjective"},{"category":"Basics-1","learnable":"bin","normalized":"bin","translation":"(أنا) أكون","partOfSpeech":"Verb"},{"category":"Basics-1","learnable":"bist","normalized":"bist","translation":"(أنت) تكون, تكون","partOfSpeech":"Verb"},{"category":"Basics-1","learnable":"brot","normalized":"brot","translation":null,"partOfSpeech":"Neuter Noun"},{"category":"Basics-1","learnable":"du","normalized":"du","translation":"أنت, أنتى, إنت","partOfSpeech":"Pronoun"},{"category":"Basics-1","learnable":"eine","normalized":"eine","translation":"واحد, حبة, واحدة, أداة تنكير المؤنث","partOfSpeech":"Feminine Determiner"},{"category":"Basics-1","learnable":"er","normalized":"er","translation":"هو, هو (مذكر), أنه","partOfSpeech":"Masculine Pronoun"},{"category":"Basics-1","learnable":"es","normalized":"es","translation":"إنه, هذا, هو, بذلك, ذلك, هو\/هي (محايد غائب)","partOfSpeech":"Neuter Pronoun"},{"category":"Basics-1","learnable":"frau","normalized":"frau","translation":null,"partOfSpeech":"Feminine Noun"},{"category":"Basics-1","learnable":"ich","normalized":"ich","translation":"أنا, أنني","partOfSpeech":"Pronoun"},{"category":"Basics-1","learnable":"ist","normalized":"ist","translation":"(هو) يكون, (هي) تكون, سيكون, توجد, هو","partOfSpeech":"Verb"},{"category":"Basics-1","learnable":"junge","normalized":"junge","translation":"الصغيرة, صغيرة","partOfSpeech":"Masculine Noun"},{"category":"Basics-1","learnable":"kind","normalized":"kind","translation":null,"partOfSpeech":"Neuter Noun"},{"category":"Basics-1","learnable":"mädchen","normalized":"madchen","translation":null,"partOfSpeech":"Neuter Noun"},{"category":"Basics-1","learnable":"mann","normalized":"mann","translation":null,"partOfSpeech":"Masculine Noun"},{"category":"Basics-1","learnable":"trinkt","normalized":"trinkt","translation":"تشرب, يشرب, اشربوا, شرب","partOfSpeech":"Verb"},{"category":"Basics-1","learnable":"und","normalized":"und","translation":"و","partOfSpeech":"Conjunction"},{"category":"Basics-1","learnable":"wasser","normalized":"wasser","translation":null,"partOfSpeech":"Neuter Noun"},{"category":"Basics-2","learnable":"das","normalized":"das","translation":"هذا, هو, ذلك, ال تعريف المحايد, الأمر, الذى, الذي, الذي (محايد), بذلك, تلك","partOfSpeech":"Neuter Pronoun"},{"category":"Basics-2","learnable":"frauen","normalized":"frauen","translation":null,"partOfSpeech":"Feminine Noun"},{"category":"Basics-2","learnable":"kinder","normalized":"kinder","translation":null,"partOfSpeech":"Neuter Noun"},{"category":"Basics-2","learnable":"männer","normalized":"manner","translation":null,"partOfSpeech":"Masculine Noun"},{"category":"Basics-2","learnable":"seid","normalized":"seid","translation":"(أنتم) تكونون, كونوا","partOfSpeech":"Verb"},{"category":"Basics-2","learnable":"sind","normalized":"sind","translation":"هي, (نحن) نكون, (هم) يكونون, تكون, موجودة, يكونوا, يوجد","partOfSpeech":"Verb"},{"category":"Basics-2","learnable":"wir","normalized":"wir","translation":"نحن, إننا","partOfSpeech":"Pronoun"},{"category":"Body-2","learnable":"dick","normalized":"dick","translation":"سمين, بدين","partOfSpeech":"Adjective"},{"category":"Body-2","learnable":"dünn","normalized":"dunn","translation":"نحيل, نحيلًا, السمينة, رفيع","partOfSpeech":"Adjective"},{"category":"Business-1","learnable":"großartig","normalized":"grossartig","translation":"عظيمًا, عظيم","partOfSpeech":"Adjective"},{"category":"Colors","learnable":"blau","normalized":"blau","translation":"أزرق, زرقاء, الأزرق","partOfSpeech":"Adjective"},{"category":"Colors","learnable":"braun","normalized":"braun","translation":"بني","partOfSpeech":"Adjective"},{"category":"Colors","learnable":"bunt","normalized":"bunt","translation":"ملون, ملونة","partOfSpeech":"Adjective"},{"category":"Colors","learnable":"gelb","normalized":"gelb","translation":"صفراء, أصفر, الصفراء","partOfSpeech":"Adjective"},{"category":"Colors","learnable":"grau","normalized":"grau","translation":"رمادى, رمادية, رمادي, رماديًا","partOfSpeech":"Adjective"},{"category":"Colors","learnable":"grün","normalized":"grun","translation":"أخضر, خضراء, الأخضر","partOfSpeech":"Adjective"},{"category":"Colors","learnable":"pink","normalized":"pink","translation":"وردى, الزهرى, زهرى, وردي","partOfSpeech":"Adjective"},{"category":"Colors","learnable":"rot","normalized":"rot","translation":"أحمر, حمراء, المفتوح","partOfSpeech":"Adjective"},{"category":"Colors","learnable":"schwarz","normalized":"schwarz","translation":"سوداء, أسود","partOfSpeech":"Adjective"},{"category":"Colors","learnable":"weiß","normalized":"weiss","translation":"بيضاء, (أنا) أعرف, أبيض, (هو) يعرف, تعرف","partOfSpeech":"Adjective"},{"category":"Common-Phrases","learnable":"auf wiedersehen","normalized":"auf wiedersehen","translation":null,"partOfSpeech":null},{"category":"Common-Phrases","learnable":"bis bald","normalized":"bis bald","translation":"أراك قريباً","partOfSpeech":null},{"category":"Common-Phrases","learnable":"bis morgen","normalized":"bis morgen","translation":"أراك غداً","partOfSpeech":null},{"category":"Common-Phrases","learnable":"bis später","normalized":"bis spater","translation":"أراك لاحقاً","partOfSpeech":null},{"category":"Common-Phrases","learnable":"bitte","normalized":"bitte","translation":"من فضلك, من فضلكم, (أنا) ألتمس, أتوسل, أرجوك, إذا سمحت, الرجاء, رجاءً, لطفاً, لو سمحت, لو سمحتم","partOfSpeech":"Adverb"},{"category":"Common-Phrases","learnable":"danke","normalized":"danke","translation":"شكراً لك, أشكر","partOfSpeech":"Interjection"},{"category":"Common-Phrases","learnable":"es tut mir leid","normalized":"es tut mir leid","translation":"[أنا] آسف","partOfSpeech":null},{"category":"Common-Phrases","learnable":"genau","normalized":"genau","translation":"بالضبط, بدقة, دقيقة, تماماً, دقيق, دقيقاً","partOfSpeech":null},{"category":"Common-Phrases","learnable":"gern geschehen","normalized":"gern geschehen","translation":null,"partOfSpeech":null},{"category":"Common-Phrases","learnable":"gute nacht","normalized":"gute nacht","translation":null,"partOfSpeech":null},{"category":"Common-Phrases","learnable":"guten abend","normalized":"guten abend","translation":null,"partOfSpeech":null},{"category":"Common-Phrases","learnable":"guten morgen","normalized":"guten morgen","translation":null,"partOfSpeech":null},{"category":"Common-Phrases","learnable":"guten tag","normalized":"guten tag","translation":null,"partOfSpeech":null},{"category":"Common-Phrases","learnable":"hallo","normalized":"hallo","translation":"مرحباً, مرحباً بك, أهلاً","partOfSpeech":"Interjection"},{"category":"Common-Phrases","learnable":"in ordnung","normalized":"in ordnung","translation":null,"partOfSpeech":null},{"category":"Common-Phrases","learnable":"ja","normalized":"ja","translation":"نعم","partOfSpeech":"Adverb"},{"category":"Common-Phrases","learnable":"leider","normalized":"leider","translation":"للأسف","partOfSpeech":"Adverb"},{"category":"Common-Phrases","learnable":"mir geht's gut","normalized":"mir geht's gut","translation":"أنا بخير","partOfSpeech":null},{"category":"Common-Phrases","learnable":"nein","normalized":"nein","translation":"لا, كلا","partOfSpeech":"Adverb"},{"category":"Common-Phrases","learnable":"tschüss","normalized":"tschuss","translation":"وداعاً, إلى اللقاء, مع السلامة, الوداع","partOfSpeech":"Interjection"},{"category":"Common-Phrases","learnable":"wie geht's","normalized":"wie geht's","translation":"كيف الحال, كيف حالك","partOfSpeech":null},{"category":"Common-Phrases","learnable":"willkommen","normalized":"willkommen","translation":"أهلاً, مرحب, مُرحب, (كصفة) مرحبٌ به, أهلاً بك, مُرحب به","partOfSpeech":"Adjective"},{"category":"Common-Phrases-2","learnable":"naja","normalized":"naja","translation":null,"partOfSpeech":"Interjection"},{"category":"Common-Phrases-2","learnable":"verzeihung","normalized":"verzeihung","translation":null,"partOfSpeech":"Feminine Noun"},{"category":"Communication-1","learnable":"fernsehen","normalized":"fernsehen","translation":"مشاهدة التلفاز","partOfSpeech":"Verb"},{"category":"Communication-2","learnable":"briefkasten","normalized":"briefkasten","translation":null,"partOfSpeech":"Masculine Noun"},{"category":"Comparisons","learnable":"besser","normalized":"besser","translation":"أفضل","partOfSpeech":"Adjective"},{"category":"Comparisons","learnable":"größer","normalized":"grosser","translation":"أكبر, الأطول","partOfSpeech":"Adjective"},{"category":"Comparisons","learnable":"höher","normalized":"hoher","translation":"أعلى","partOfSpeech":"Adjective"},{"category":"Comparisons","learnable":"kleiner","normalized":"kleiner","translation":"أصغر, صغير (مذكر بعد أداة نكرة)","partOfSpeech":"Adjective"},{"category":"Comparisons","learnable":"länger","normalized":"langer","translation":"أطول","partOfSpeech":"Adjective"},{"category":"Comparisons","learnable":"langsamer","normalized":"langsamer","translation":"أبطأ, بشكل أبطأ, بطيء","partOfSpeech":"Adjective"},{"category":"Comparisons","learnable":"leichter","normalized":"leichter","translation":"أسهل, أخف","partOfSpeech":"Adjective"},{"category":"Comparisons","learnable":"schöner","normalized":"schoner","translation":"أجمل, جميلة, جميل, أجمل (مقارنة)","partOfSpeech":"Adjective"},{"category":"Comparisons","learnable":"stärker","normalized":"starker","translation":"أقوى","partOfSpeech":"Adjective"},{"category":"Comparisons","learnable":"wichtiger","normalized":"wichtiger","translation":"أهم, أكثر أهمية","partOfSpeech":"Adjective"},{"category":"Conjunctions","learnable":"aber","normalized":"aber","translation":"لكن, ولكن","partOfSpeech":"Conjunction"},{"category":"Conjunctions","learnable":"da","normalized":"da","translation":"هناك, هنا, هنالك, حيث, لأن","partOfSpeech":"Conjunction"},{"category":"Conjunctions","learnable":"dass","normalized":"dass","translation":"أن, أنه, أني, بأنه","partOfSpeech":"Conjunction"},{"category":"Conjunctions","learnable":"denn","normalized":"denn","translation":"إذًا, لأن","partOfSpeech":"Conjunction"},{"category":"Conjunctions","learnable":"doch","normalized":"doch","translation":"بالتأكيد, لكنه","partOfSpeech":"Conjunction"},{"category":"Conjunctions","learnable":"entweder","normalized":"entweder","translation":"إما","partOfSpeech":"Conjunction"},{"category":"Conjunctions","learnable":"obwohl","normalized":"obwohl","translation":"رغم, رغم أن","partOfSpeech":"Conjunction"},{"category":"Conjunctions","learnable":"oder","normalized":"oder","translation":"أم, أو, أليس كذلك؟","partOfSpeech":"Conjunction"},{"category":"Conjunctions","learnable":"sobald","normalized":"sobald","translation":"فور","partOfSpeech":"Conjunction"},{"category":"Conjunctions","learnable":"solange","normalized":"solange","translation":"طالما","partOfSpeech":"Conjunction"},{"category":"Conjunctions","learnable":"sondern","normalized":"sondern","translation":"بل, و لكن","partOfSpeech":"Conjunction"},{"category":"Conjunctions","learnable":"weil","normalized":"weil","translation":"لأن","partOfSpeech":"Conjunction"},{"category":"Conjunctions","learnable":"wenn","normalized":"wenn","translation":"عندما, إذا, لو, اذا","partOfSpeech":"Conjunction"},{"category":"Dates-1","learnable":"bald","normalized":"bald","translation":"قريبًا","partOfSpeech":"Adverb"},{"category":"Dates-1","learnable":"bis","normalized":"bis","translation":"إلى, حتى","partOfSpeech":"Preposition"},{"category":"Dates-1","learnable":"danach","normalized":"danach","translation":"بعدها, بعد ذلك","partOfSpeech":"Adverb"},{"category":"Dates-1","learnable":"endlich","normalized":"endlich","translation":"أخيرًا","partOfSpeech":"Adverb"},{"category":"Dates-1","learnable":"inzwischen","normalized":"inzwischen","translation":"في هذه الأثناء, في نفس الوقت","partOfSpeech":"Adverb"},{"category":"Dates-1","learnable":"spätestens","normalized":"spatestens","translation":"على أقصى تقدير","partOfSpeech":"Adverb"},{"category":"Dates-1","learnable":"täglich","normalized":"taglich","translation":"يومياً, اليومية","partOfSpeech":"Adjective"},{"category":"Dates-1","learnable":"wöchentlich","normalized":"wochentlich","translation":"أسبوعيًا","partOfSpeech":"Adjective"},{"category":"Dates-2","learnable":"heiß","normalized":"heiss","translation":"ساخن, حار","partOfSpeech":"Adjective"},{"category":"Dates-2","learnable":"jährlich","normalized":"jahrlich","translation":null,"partOfSpeech":"Adjective"},{"category":"Dates-2","learnable":"kühl","normalized":"kuhl","translation":"باردة, بارد, رطب, فاتر","partOfSpeech":"Adjective"},{"category":"Dates-2","learnable":"monatlich","normalized":"monatlich","translation":"شهريًا, كل شهر, شهرياً","partOfSpeech":"Adjective"},{"category":"Dates-2","learnable":"vorbei","normalized":"vorbei","translation":"منتهى, عبر, محسوم","partOfSpeech":"Adverb"},{"category":"Dative-Case","learnable":"dem","normalized":"dem","translation":"ال","partOfSpeech":"Neuter Determiner"},{"category":"Dative-Case","learnable":"der","normalized":"der","translation":"الذى, ال [لتعريف المذكر]","partOfSpeech":"Feminine Determiner"},{"category":"Dative-Case","learnable":"einem","normalized":"einem","translation":"الDativ  من ein","partOfSpeech":"Masculine Determiner"},{"category":"Dative-Case","learnable":"einer","normalized":"einer","translation":"واحدة, الdativ من eine","partOfSpeech":"Feminine Determiner"},{"category":"Dative-Prepositions","learnable":"bei","normalized":"bei","translation":"عند, بجانب, بين","partOfSpeech":"Preposition"},{"category":"Dative-Prepositions","learnable":"beim","normalized":"beim","translation":"عند, فى, bei+dem","partOfSpeech":"Neuter Preposition"},{"category":"Dative-Prepositions","learnable":"mit","normalized":"mit","translation":"مع, فى, بواسطة","partOfSpeech":"Preposition"},{"category":"Dative-Prepositions","learnable":"nach","normalized":"nach","translation":"إلى, بعد, عن","partOfSpeech":"Preposition"},{"category":"Dative-Prepositions","learnable":"seit","normalized":"seit","translation":"منذ","partOfSpeech":"Preposition"},{"category":"Dative-Prepositions","learnable":"vom","normalized":"vom","translation":"من, عن, von+dem","partOfSpeech":"Masculine Preposition"},{"category":"Dative-Prepositions","learnable":"von","normalized":"von","translation":"من, عن","partOfSpeech":"Preposition"},{"category":"Dative-Prepositions","learnable":"zu","normalized":"zu","translation":"أن, إلى, جدًا, جداً","partOfSpeech":"Preposition"},{"category":"Dative-Prepositions","learnable":"zum","normalized":"zum","translation":"إلى, zu+dem","partOfSpeech":"Neuter Preposition"},{"category":"Dative-Prepositions","learnable":"zur","normalized":"zur","translation":"إلى, zu+der","partOfSpeech":"Feminine Preposition"},{"category":"Dative-Pronouns","learnable":"dir","normalized":"dir","translation":"لك, إليك, لنفسك","partOfSpeech":"Pronoun"},{"category":"Dative-Pronouns","learnable":"ihm","normalized":"ihm","translation":"له, ه","partOfSpeech":"Masculine Pronoun"},{"category":"Dative-Pronouns","learnable":"ihnen","normalized":"ihnen","translation":"لهم, بالنسبة لهم, (هم) فى حالة الجر","partOfSpeech":"Pronoun"},{"category":"Dative-Pronouns","learnable":"ihr","normalized":"ihr","translation":"أنتم, لها, أنتن, (خاصتها\/ملكها), أنتما, إليها","partOfSpeech":"Feminine Pronoun"},{"category":"Dative-Pronouns","learnable":"meinem","normalized":"meinem","translation":"(خاصتي\/ملكي)","partOfSpeech":"Masculine Pronoun"},{"category":"Dative-Pronouns","learnable":"meinen","normalized":"meinen","translation":"(ملكي\/خاصتي)","partOfSpeech":"Pronoun"},{"category":"Dative-Pronouns","learnable":"meiner","normalized":"meiner","translation":"ضمير ملكية فى الdativ, dativ ل meine","partOfSpeech":"Feminine Pronoun"},{"category":"Dative-Pronouns","learnable":"mir","normalized":"mir","translation":"لي, لى, (نفسي\/لي), بى, لنفسى, لنفسي","partOfSpeech":"Pronoun"},{"category":"Dative-Pronouns","learnable":"uns","normalized":"uns","translation":"لنا, إلينا, أنفسنا, إيانا, ـنا","partOfSpeech":"Pronoun"},{"category":"Direction","learnable":"her","normalized":"her","translation":"هنا, إلى هنا","partOfSpeech":"Adverb"},{"category":"Direction","learnable":"heraus","normalized":"heraus","translation":"إلى الخارج","partOfSpeech":"Adverb"},{"category":"Direction","learnable":"herein","normalized":"herein","translation":"إلى الداخل","partOfSpeech":"Adverb"},{"category":"Direction","learnable":"herum","normalized":"herum","translation":"حول, حوالى","partOfSpeech":"Adverb"},{"category":"Direction","learnable":"hierher","normalized":"hierher","translation":"إلى هنا","partOfSpeech":"Adverb"},{"category":"Direction","learnable":"hin","normalized":"hin","translation":"إلى","partOfSpeech":"Adverb"},{"category":"Direction","learnable":"hinaus","normalized":"hinaus","translation":"إلى الخارج, خارجًا","partOfSpeech":"Adverb"},{"category":"Direction","learnable":"links","normalized":"links","translation":"ناحية اليسار, يسارًا, يساراً","partOfSpeech":"Adverb"},{"category":"Direction","learnable":"raus","normalized":"raus","translation":"يخرج, فى الخارج","partOfSpeech":"Adverb"},{"category":"Direction","learnable":"rechts","normalized":"rechts","translation":"ناحية اليمين, يمينًا, يميناً","partOfSpeech":"Adverb"},{"category":"Direction","learnable":"rein","normalized":"rein","translation":"إلى الداخل","partOfSpeech":"Adverb"},{"category":"Direction","learnable":"unterwegs","normalized":"unterwegs","translation":"فى الطريق","partOfSpeech":"Adverb"},{"category":"Direction","learnable":"voraus","normalized":"voraus","translation":"إلى الأمام, نحو الأمام","partOfSpeech":"Adverb"},{"category":"Direction","learnable":"weg","normalized":"weg","translation":"بعيدًا, بعيد","partOfSpeech":"Adverb"},{"category":"Direction","learnable":"woher","normalized":"woher","translation":null,"partOfSpeech":"Adverb"},{"category":"Direction","learnable":"zurück","normalized":"zuruck","translation":"إلى الوراء","partOfSpeech":"Adverb"},{"category":"Family-2","learnable":"schwanger","normalized":"schwanger","translation":"حامل","partOfSpeech":"Adjective"},{"category":"Family-2","learnable":"verheiratet","normalized":"verheiratet","translation":"متزوج, متزوجان, متزوجة, متزوجون","partOfSpeech":"Adjective"},{"category":"Fantasy-&-Science-Fiction","learnable":"magie","normalized":"magie","translation":null,"partOfSpeech":"Feminine Noun"},{"category":"Fantasy-&-Science-Fiction","learnable":"magisch","normalized":"magisch","translation":"سحرى, ساحرة, سحرية, ساحر","partOfSpeech":"Adjective"},{"category":"Fantasy-&-Science-Fiction","learnable":"unglaublich","normalized":"unglaublich","translation":"لا يُصدّق","partOfSpeech":"Adjective"},{"category":"Feelings","learnable":"dumm","normalized":"dumm","translation":"غبى, غبيا","partOfSpeech":"Adjective"},{"category":"Feelings","learnable":"ehrlich","normalized":"ehrlich","translation":"صريحًا, صريحة, بصراحة, حقاً, صادق, صريح","partOfSpeech":"Adjective"},{"category":"Feelings","learnable":"gar","normalized":"gar","translation":"على الإطلاق","partOfSpeech":"Adverb"},{"category":"Feelings","learnable":"interessant","normalized":"interessant","translation":"شيقة, مثيرة, مثير, شيق, ممتع","partOfSpeech":"Adjective"},{"category":"Feelings","learnable":"langweilig","normalized":"langweilig","translation":"ممل, مملة","partOfSpeech":"Adjective"},{"category":"Feelings","learnable":"lieber","normalized":"lieber","translation":"أفضل, (هو) يُفضل","partOfSpeech":"Adjective"},{"category":"Feelings","learnable":"nett","normalized":"nett","translation":"لطيفة, لطيفًا, لطيف","partOfSpeech":"Adjective"},{"category":"Feelings","learnable":"schlau","normalized":"schlau","translation":"ذكى, ذكيا, ذكي","partOfSpeech":"Adjective"},{"category":"Feelings","learnable":"schlimm","normalized":"schlimm","translation":"سيئ, فظيع","partOfSpeech":"Adjective"},{"category":"Feelings","learnable":"stolz","normalized":"stolz","translation":"فخورون, فخور, فخورة","partOfSpeech":"Adjective"},{"category":"Feelings","learnable":"tapfer","normalized":"tapfer","translation":"بشجاعة, شجاعة, شجاع, ببسالة","partOfSpeech":"Adjective"},{"category":"Feelings","learnable":"total","normalized":"total","translation":"كليًا, تمامًا","partOfSpeech":"Adjective"},{"category":"Feelings","learnable":"unheimlich","normalized":"unheimlich","translation":"مخيف, مخيفة, بشكل رهيب","partOfSpeech":"Adjective"},{"category":"Feelings","learnable":"witzig","normalized":"witzig","translation":"ظريف, ظريفًا, مضحك","partOfSpeech":"Adjective"},{"category":"Food","learnable":"durst","normalized":"durst","translation":null,"partOfSpeech":"Masculine Noun"},{"category":"Food","learnable":"eis","normalized":"eis","translation":null,"partOfSpeech":"Neuter Noun"},{"category":"Food","learnable":"frisch","normalized":"frisch","translation":"طازجة, طازج","partOfSpeech":"Adjective"},{"category":"Food","learnable":"gut","normalized":"gut","translation":"جيد, جيدة, بشكل جيد, [جيد\/خير], بخير, جيداً, جيدين, طيب","partOfSpeech":"Adjective"},{"category":"Food","learnable":"hunger","normalized":"hunger","translation":null,"partOfSpeech":"Masculine Noun"},{"category":"Food","learnable":"lecker","normalized":"lecker","translation":"لذيذ, لذيذة","partOfSpeech":"Adjective"},{"category":"Food","learnable":"schmeckt","normalized":"schmeckt","translation":"طعمه, طعمها, يتذوق, (شيء) طعمه .., طعم, مذاقه","partOfSpeech":"Verb"},{"category":"Food","learnable":"süß","normalized":"suss","translation":"حلو, حلوة, حلوين, لذيذ","partOfSpeech":"Adjective"},{"category":"Food-2","learnable":"butter","normalized":"butter","translation":null,"partOfSpeech":"Feminine Noun"},{"category":"Food-2","learnable":"marmelade","normalized":"marmelade","translation":null,"partOfSpeech":"Feminine Noun"},{"category":"Food-2","learnable":"messer","normalized":"messer","translation":null,"partOfSpeech":"Neuter Noun"},{"category":"Food-2","learnable":"müsli","normalized":"musli","translation":null,"partOfSpeech":"Neuter Noun"},{"category":"Food-2","learnable":"salat","normalized":"salat","translation":null,"partOfSpeech":"Masculine Noun"},{"category":"Food-2","learnable":"salzig","normalized":"salzig","translation":"مالح, مالحة","partOfSpeech":"Adjective"},{"category":"Food-2","learnable":"sauer","normalized":"sauer","translation":"حامضة, غاضبة, غاضبين, حامض, حامضي, مخلل","partOfSpeech":"Adjective"},{"category":"Food-2","learnable":"scharf","normalized":"scharf","translation":"حار, حاد","partOfSpeech":"Adjective"},{"category":"Food-2","learnable":"zu abend","normalized":"zu abend","translation":null,"partOfSpeech":null},{"category":"Food-2","learnable":"zu mittag","normalized":"zu mittag","translation":null,"partOfSpeech":null},{"category":"Frequency","learnable":"als","normalized":"als","translation":"من (مقارنة), لمّا, عندما","partOfSpeech":"Conjunction"},{"category":"Frequency","learnable":"bisschen","normalized":"bisschen","translation":null,"partOfSpeech":"Determiner"},{"category":"Frequency","learnable":"desto","normalized":"desto","translation":"كلما","partOfSpeech":"Conjunction"},{"category":"Frequency","learnable":"häufig","normalized":"haufig","translation":"كثيراً ما, غالباً","partOfSpeech":"Adjective"},{"category":"Frequency","learnable":"je","normalized":"je","translation":"كلما, أبدًا","partOfSpeech":"Adverb"},{"category":"Frequency","learnable":"keinerlei","normalized":"keinerlei","translation":"أي","partOfSpeech":"Determiner"},{"category":"Frequency","learnable":"manchmal","normalized":"manchmal","translation":"أحياناً","partOfSpeech":"Adverb"},{"category":"Frequency","learnable":"mehr","normalized":"mehr","translation":"أكثر, المزيد, مزيد, الكثير, بعد الآن","partOfSpeech":"Adverb"},{"category":"Frequency","learnable":"meist","normalized":"meist","translation":"غالبًا","partOfSpeech":"Adverb"},{"category":"Frequency","learnable":"ob","normalized":"ob","translation":"إذا, هل","partOfSpeech":"Conjunction"},{"category":"Frequency","learnable":"oft","normalized":"oft","translation":"كثيرًا, غالبًا, غالبا","partOfSpeech":"Adverb"},{"category":"Frequency","learnable":"selten","normalized":"selten","translation":"نادرًا, نادر, نادراً","partOfSpeech":"Adjective"},{"category":"Frequency","learnable":"weniger","normalized":"weniger","translation":"أقل","partOfSpeech":"Adverb"},{"category":"Genitive-Case","learnable":"des","normalized":"des","translation":"اليوم, الإضافة (مذكر\/ محايد)","partOfSpeech":"Masculine Determiner"},{"category":"Genitive-Case","learnable":"eines","normalized":"eines","translation":"أحدهم, أحد","partOfSpeech":"Neuter Determiner"},{"category":"German-Culture","learnable":"sauerkraut","normalized":"sauerkraut","translation":null,"partOfSpeech":"Neuter Noun"},{"category":"German-Culture","learnable":"tag der deutschen einheit","normalized":"tag der deutschen einheit","translation":null,"partOfSpeech":null},{"category":"Household-2","learnable":"leer","normalized":"leer","translation":"فارغة, فارغ","partOfSpeech":"Adjective"},{"category":"Household-2","learnable":"voll","normalized":"voll","translation":"ممتلئة, ممتلئ, الممتلئ","partOfSpeech":"Adjective"},{"category":"Internet-&-Social-Media","learnable":"herunter","normalized":"herunter","translation":null,"partOfSpeech":"Adverb"},{"category":"Internet-&-Social-Media","learnable":"hoch","normalized":"hoch","translation":"مرتفع, عالٍ, عالية, عالي, عالياً, كبيرة, مرتفعان, مرتفعة, مرتفعًا","partOfSpeech":null},{"category":"Introduction","learnable":"ägypten","normalized":"agypten","translation":null,"partOfSpeech":"Neuter Proper noun"},{"category":"Introduction","learnable":"arabisch","normalized":"arabisch","translation":null,"partOfSpeech":"Neuter Noun"},{"category":"Introduction","learnable":"aus","normalized":"aus","translation":"من, خارج","partOfSpeech":"Preposition"},{"category":"Introduction","learnable":"deutsch","normalized":"deutsch","translation":null,"partOfSpeech":"Neuter Noun"},{"category":"Introduction","learnable":"englisch","normalized":"englisch","translation":null,"partOfSpeech":"Neuter Noun"},{"category":"Introduction","learnable":"hans","normalized":"hans","translation":null,"partOfSpeech":"Masculine Proper noun"},{"category":"Introduction","learnable":"syrien","normalized":"syrien","translation":null,"partOfSpeech":"Neuter Proper noun"},{"category":"Location","learnable":"außen","normalized":"aussen","translation":"الخارج","partOfSpeech":"Adverb"},{"category":"Location","learnable":"dort","normalized":"dort","translation":"هناك","partOfSpeech":"Adverb"},{"category":"Location","learnable":"draußen","normalized":"draussen","translation":"فى الخارج","partOfSpeech":"Adverb"},{"category":"Location","learnable":"drinnen","normalized":"drinnen","translation":"فى الداخل","partOfSpeech":"Adverb"},{"category":"Location","learnable":"drüben","normalized":"druben","translation":"هناك","partOfSpeech":"Adverb"},{"category":"Location","learnable":"hier","normalized":"hier","translation":"هنا","partOfSpeech":"Adverb"},{"category":"Location","learnable":"hinten","normalized":"hinten","translation":"فى الخلف, الخلف","partOfSpeech":"Adverb"},{"category":"Location","learnable":"innen","normalized":"innen","translation":"الداخل","partOfSpeech":"Adverb"},{"category":"Location","learnable":"nebenan","normalized":"nebenan","translation":"مجاور, المجاور, بالجوار","partOfSpeech":"Adverb"},{"category":"Location","learnable":"oben","normalized":"oben","translation":"فى الأعلى","partOfSpeech":"Adverb"},{"category":"Location","learnable":"überall","normalized":"uberall","translation":"فى كل مكان","partOfSpeech":"Adverb"},{"category":"Location","learnable":"unten","normalized":"unten","translation":"فى الأسفل, لأسفل, الأسفل","partOfSpeech":"Adverb"},{"category":"Location","learnable":"vorne","normalized":"vorne","translation":"فى المقدمة","partOfSpeech":"Adverb"},{"category":"Materials","learnable":"glas","normalized":"glas","translation":null,"partOfSpeech":"Neuter Noun"},{"category":"Math","learnable":"gleich","normalized":"gleich","translation":"يساوى, فى الحال, للتو","partOfSpeech":"Adverb"},{"category":"Math","learnable":"minus","normalized":"minus","translation":"ناقص","partOfSpeech":"Preposition"},{"category":"Math","learnable":"plus","normalized":"plus","translation":"زائد, موجب","partOfSpeech":"Adverb"},{"category":"Medical","learnable":"krank","normalized":"krank","translation":"مريض, مريضون, مريضة","partOfSpeech":"Adjective"},{"category":"Money","learnable":"reich","normalized":"reich","translation":"أغنياء, غني, غنية, الغني, الغنية, غنى","partOfSpeech":"Adjective"},{"category":"Negatives","learnable":"kein","normalized":"kein","translation":"لا, ليس, ليست, لست, ليس بـ","partOfSpeech":"Neuter Determiner"},{"category":"Negatives","learnable":"keine","normalized":"keine","translation":"ليس, لا, ليست, أي, أية, لسنا, لم, لن, ليست بـ, ليسوا","partOfSpeech":"Determiner"},{"category":"Negatives","learnable":"keinen","normalized":"keinen","translation":"لا, ليس, لم","partOfSpeech":"Masculine Determiner"},{"category":"Negatives","learnable":"keiner","normalized":"keiner","translation":"لا أحد","partOfSpeech":"Masculine Determiner"},{"category":"Negatives","learnable":"nie","normalized":"nie","translation":"لا, أبداً, إطلاقاً, إطلاقاّ, لن","partOfSpeech":"Adverb"},{"category":"Negatives","learnable":"niemals","normalized":"niemals","translation":"أبداً, أبدًا","partOfSpeech":"Adverb"},{"category":"Nominative-Pronouns","learnable":"alle","normalized":"alle","translation":"كل, جميع, الكل, جميعاً, جميعها, كلنا, كلهم","partOfSpeech":"Determiner"},{"category":"Nominative-Pronouns","learnable":"alles","normalized":"alles","translation":"كل, كل شيء, شئ, كله","partOfSpeech":"Neuter Determiner"},{"category":"Nominative-Pronouns","learnable":"etwas","normalized":"etwas","translation":"شيئًا, شيء, شيء ما, بعض, شئ, شيئاً, شيئاً ما, نوعاً ما (ظرف)","partOfSpeech":"Neuter Pronoun"},{"category":"Nominative-Pronouns","learnable":"jemand","normalized":"jemand","translation":"أحد, أحد ما, شخص","partOfSpeech":"Determiner"},{"category":"Nominative-Pronouns","learnable":"niemand","normalized":"niemand","translation":"أحد, لا أحد","partOfSpeech":"Determiner"},{"category":"Nominative-Pronouns","learnable":"paar","normalized":"paar","translation":"زوج","partOfSpeech":"Determiner"},{"category":"Nominative-Pronouns","learnable":"viel","normalized":"viel","translation":"الكثير, الكثير من, كبيرة, كتيرا, كثير, كثيراً, كثيرة, كثيرًا","partOfSpeech":"Determiner"},{"category":"Not","learnable":"einfach","normalized":"einfach","translation":"بسيط, ببساطة, سهلة, بسيطاً, بسيطة, سهل, سهلًا","partOfSpeech":"Adjective"},{"category":"Not","learnable":"fertig","normalized":"fertig","translation":"جاهز, جاهزة, جاهزاً, جهز, مستعد, منهك","partOfSpeech":"Adjective"},{"category":"Not","learnable":"gesund","normalized":"gesund","translation":"بصحة جيدة, صحي, صحية, معافى","partOfSpeech":"Adjective"},{"category":"Not","learnable":"lustig","normalized":"lustig","translation":"مضحك, مضحكة, ظريف","partOfSpeech":"Adjective"},{"category":"Not","learnable":"nicht","normalized":"nicht","translation":"لا, ليس, ليست, ألّا, غير, لست, لسن, لسنا, لم, لن, ليسوا","partOfSpeech":"Adverb"},{"category":"Not","learnable":"stark","normalized":"stark","translation":"قوي, قوية, أقوياء, القوية, قوياً","partOfSpeech":"Adjective"},{"category":"Not","learnable":"traurig","normalized":"traurig","translation":"حزين, حزيناً, حزينة, حزانى, حزينات, حزينين","partOfSpeech":"Adjective"},{"category":"Numbers-1","learnable":"acht","normalized":"acht","translation":"ثمانية, الثامنة, ثمانى, ثماني, ثمانِ","partOfSpeech":"Numeral"},{"category":"Numbers-1","learnable":"achtzehn","normalized":"achtzehn","translation":"ثمانية عشر","partOfSpeech":"Numeral"},{"category":"Numbers-1","learnable":"drei","normalized":"drei","translation":"ثلاثة, ثلاث","partOfSpeech":"Numeral"},{"category":"Numbers-1","learnable":"dreizehn","normalized":"dreizehn","translation":"ثلاثة عشر, ثلاث عشرة","partOfSpeech":"Numeral"},{"category":"Numbers-1","learnable":"dutzend","normalized":"dutzend","translation":null,"partOfSpeech":"Neuter Noun"},{"category":"Numbers-1","learnable":"eins","normalized":"eins","translation":"واحد","partOfSpeech":"Numeral"},{"category":"Numbers-1","learnable":"elf","normalized":"elf","translation":"إحدى عشر","partOfSpeech":"Numeral"},{"category":"Numbers-1","learnable":"es gibt","normalized":"es gibt","translation":"هناك, يوجد","partOfSpeech":null},{"category":"Numbers-1","learnable":"fünf","normalized":"funf","translation":"خمسة, خمس, الخمسة","partOfSpeech":"Numeral"},{"category":"Numbers-1","learnable":"fünfzehn","normalized":"funfzehn","translation":"خمسة عشر, خمس عشرة","partOfSpeech":"Numeral"},{"category":"Numbers-1","learnable":"neun","normalized":"neun","translation":"تسعة, تسع, التاسعة","partOfSpeech":"Numeral"},{"category":"Numbers-1","learnable":"neunzehn","normalized":"neunzehn","translation":"تسعة عشر","partOfSpeech":"Numeral"},{"category":"Numbers-1","learnable":"sechs","normalized":"sechs","translation":"ستة, السادسة, ست","partOfSpeech":"Numeral"},{"category":"Numbers-1","learnable":"sechzehn","normalized":"sechzehn","translation":"ستة عشر","partOfSpeech":"Numeral"},{"category":"Numbers-1","learnable":"sieben","normalized":"sieben","translation":"سبعة, سبع","partOfSpeech":"Numeral"},{"category":"Numbers-1","learnable":"siebzehn","normalized":"siebzehn","translation":"سبعة عشر","partOfSpeech":"Numeral"},{"category":"Numbers-1","learnable":"vier","normalized":"vier","translation":"أربعة, أربع","partOfSpeech":"Numeral"},{"category":"Numbers-1","learnable":"vierzehn","normalized":"vierzehn","translation":"أربعة عشر","partOfSpeech":"Numeral"},{"category":"Numbers-1","learnable":"zehn","normalized":"zehn","translation":"عشرة, عشر, العشرة, عشرعامًًا","partOfSpeech":"Numeral"},{"category":"Numbers-1","learnable":"zwei","normalized":"zwei","translation":"اثنين, اثنان, إثنان, إثنتى, اثنتى, اثنى","partOfSpeech":"Numeral"},{"category":"Numbers-1","learnable":"zwölf","normalized":"zwolf","translation":"اثنتى عشرة, إثنى عشر, إثنا عشر","partOfSpeech":"Numeral"},{"category":"Numbers-2","learnable":"achtundzwanzig","normalized":"achtundzwanzig","translation":"ثمانٍ وعشرون, ثمانية وعشرون","partOfSpeech":"Numeral"},{"category":"Numbers-2","learnable":"achtzig","normalized":"achtzig","translation":"ثمانون, ثمانين","partOfSpeech":"Numeral"},{"category":"Numbers-2","learnable":"dreißig","normalized":"dreissig","translation":"ثلاثون, ثلاثين","partOfSpeech":"Numeral"},{"category":"Numbers-2","learnable":"dreiundzwanzig","normalized":"dreiundzwanzig","translation":"ثلاثة وعشرون","partOfSpeech":"Numeral"},{"category":"Numbers-2","learnable":"einundzwanzig","normalized":"einundzwanzig","translation":"واحد وعشرون","partOfSpeech":"Numeral"},{"category":"Numbers-2","learnable":"fünfzig","normalized":"funfzig","translation":"خمسون, خمسين","partOfSpeech":"Numeral"},{"category":"Numbers-2","learnable":"hundert","normalized":"hundert","translation":"مائة","partOfSpeech":"Numeral"},{"category":"Numbers-2","learnable":"hundertdreiundzwanzig","normalized":"hundertdreiundzwanzig","translation":"مائة وثلاثة وعشرون","partOfSpeech":"Numeral"},{"category":"Numbers-2","learnable":"neunzig","normalized":"neunzig","translation":"تسعون, التسعين, تسعين","partOfSpeech":"Numeral"},{"category":"Numbers-2","learnable":"sechzig","normalized":"sechzig","translation":"ستون, ستين","partOfSpeech":"Numeral"},{"category":"Numbers-2","learnable":"siebzig","normalized":"siebzig","translation":"سبعون, سبعين","partOfSpeech":"Numeral"},{"category":"Numbers-2","learnable":"tausend","normalized":"tausend","translation":null,"partOfSpeech":"Numeral"},{"category":"Numbers-2","learnable":"vierundzwanzig","normalized":"vierundzwanzig","translation":"أربعة وعشرون, أربع وعشرون","partOfSpeech":"Numeral"},{"category":"Numbers-2","learnable":"vierzig","normalized":"vierzig","translation":"أربعون, أربعين","partOfSpeech":"Numeral"},{"category":"Numbers-2","learnable":"zwanzig","normalized":"zwanzig","translation":"عشرون, عشرين, وعشرين","partOfSpeech":"Numeral"},{"category":"Numbers-2","learnable":"zweiundachtzig","normalized":"zweiundachtzig","translation":"اثنان وثمانون, اثنين وثمانين","partOfSpeech":"Numeral"},{"category":"Numbers-2","learnable":"zweiunddreißig","normalized":"zweiunddreissig","translation":"اثنان وثلاثون","partOfSpeech":"Numeral"},{"category":"Numbers-2","learnable":"zweiundvierzig","normalized":"zweiundvierzig","translation":"اثنين وأربعون, اثنان وأربعون","partOfSpeech":"Numeral"},{"category":"Numbers-3","learnable":"ähnlich","normalized":"ahnlich","translation":"متقارب, متقاربتان, متشابه, متشابهتان","partOfSpeech":"Adjective"},{"category":"Occupation-1","learnable":"bäckerin","normalized":"backerin","translation":null,"partOfSpeech":"Feminine Noun"},{"category":"Philosophy","learnable":"optimist","normalized":"optimist","translation":null,"partOfSpeech":null},{"category":"Philosophy","learnable":"pessimist","normalized":"pessimist","translation":null,"partOfSpeech":null},{"category":"Philosophy","learnable":"skeptisch","normalized":"skeptisch","translation":"شكاك, مرتاب","partOfSpeech":null},{"category":"Philosophy","learnable":"wahr","normalized":"wahr","translation":"حقيقى, حقيقة, حقيقيَ, صحيح","partOfSpeech":"Adjective"},{"category":"Places-2","learnable":"gegenüber","normalized":"gegenuber","translation":"مقابل, في الجانب الآخر, في الجهة المقابلة","partOfSpeech":"Preposition"},{"category":"Plurals","learnable":"bären","normalized":"baren","translation":null,"partOfSpeech":"Masculine Noun"},{"category":"Plurals","learnable":"enten","normalized":"enten","translation":null,"partOfSpeech":"Feminine Noun"},{"category":"Plurals","learnable":"kühe","normalized":"kuhe","translation":null,"partOfSpeech":"Feminine Noun"},{"category":"Plurals","learnable":"mäuse","normalized":"mause","translation":null,"partOfSpeech":"Feminine Noun"},{"category":"Plurals","learnable":"schweine","normalized":"schweine","translation":null,"partOfSpeech":"Neuter Noun"},{"category":"Plurals","learnable":"vögel","normalized":"vogel","translation":null,"partOfSpeech":"Masculine Noun"},{"category":"Politics-2","learnable":"korrupt","normalized":"korrupt","translation":"فاسد, فاسدة","partOfSpeech":"Adjective"},{"category":"Possessive-Pronouns","learnable":"dein","normalized":"dein","translation":"خاصتك, (خاصتك\/ملكك), ضمير ملكية المخاطب المفرد","partOfSpeech":"Masculine Pronoun"},{"category":"Possessive-Pronouns","learnable":"deine","normalized":"deine","translation":"ضمير ملكية المخاطب المفرد, ـك","partOfSpeech":"Feminine Pronoun"},{"category":"Possessive-Pronouns","learnable":"mein","normalized":"mein","translation":"الخاصة بى, (خاصتي), (لي)","partOfSpeech":"Masculine Pronoun"},{"category":"Possessive-Pronouns","learnable":"meine","normalized":"meine","translation":"لي, الخاصة بى, (لي), (خاصتي), (ـي), خاصتي","partOfSpeech":"Pronoun"},{"category":"Prepositions","learnable":"am","normalized":"am","translation":"على, في, فى, عند","partOfSpeech":"Masculine Preposition"},{"category":"Prepositions","learnable":"auf","normalized":"auf","translation":"على, فى, إلى, فوق","partOfSpeech":"Preposition"},{"category":"Prepositions","learnable":"aufs","normalized":"aufs","translation":"إلى, على الـ","partOfSpeech":"Neuter Preposition"},{"category":"Prepositions","learnable":"einschließlich","normalized":"einschliesslich","translation":"بما فيهم","partOfSpeech":"Preposition"},{"category":"Prepositions","learnable":"im","normalized":"im","translation":"فى, في الـ ..., على","partOfSpeech":"Masculine Preposition"},{"category":"Prepositions","learnable":"ins","normalized":"ins","translation":"إلى, in+das","partOfSpeech":"Neuter Preposition"},{"category":"Prepositions","learnable":"ums","normalized":"ums","translation":"حول","partOfSpeech":"Neuter Preposition"},{"category":"Prepositions","learnable":"während","normalized":"wahrend","translation":"أثناء","partOfSpeech":"Preposition"},{"category":"Qualifiers","learnable":"eher","normalized":"eher","translation":"بالأحرى, نوعاً ما","partOfSpeech":"Adverb"},{"category":"Qualifiers","learnable":"ganz","normalized":"ganz","translation":"كليًا, بالكامل, تمامًا, جدًا","partOfSpeech":"Adverb"},{"category":"Qualifiers","learnable":"gewöhnlich","normalized":"gewohnlich","translation":"مألوف, عادةً","partOfSpeech":"Adjective"},{"category":"Qualifiers","learnable":"normalerweise","normalized":"normalerweise","translation":"فى الأحوال العادية","partOfSpeech":"Adverb"},{"category":"Qualifiers","learnable":"sehr","normalized":"sehr","translation":"جدًا, جداً, جيدًا, جدأ, جدا, جدًًا, كثير, للغاية","partOfSpeech":"Adverb"},{"category":"Qualifiers","learnable":"super","normalized":"super","translation":"ممتاز, رائعة, ممتازة, رائع","partOfSpeech":"Adjective"},{"category":"Qualifiers","learnable":"ziemlich","normalized":"ziemlich","translation":"نوعاً ما","partOfSpeech":"Adverb"},{"category":"Religion","learnable":"heilig","normalized":"heilig","translation":"المقدس, مقدسة, مقدس","partOfSpeech":"Adjective"},{"category":"Religion","learnable":"hinduismus","normalized":"hinduismus","translation":null,"partOfSpeech":"Masculine Noun"},{"category":"Shopping","learnable":"billig","normalized":"billig","translation":"رخيص, رخيصة","partOfSpeech":"Adjective"},{"category":"Shopping","learnable":"gratis","normalized":"gratis","translation":"بالمجان, مجاني, مجانية","partOfSpeech":"Adverb"},{"category":"Some-","learnable":"irgendwann","normalized":"irgendwann","translation":"وقتًا ما, وقت ما","partOfSpeech":"Adverb"},{"category":"Some-","learnable":"irgendwas","normalized":"irgendwas","translation":"شئ ما","partOfSpeech":"Neuter Determiner"},{"category":"Some-","learnable":"irgendwer","normalized":"irgendwer","translation":null,"partOfSpeech":"Determiner"},{"category":"Some-","learnable":"irgendwie","normalized":"irgendwie","translation":"نوعاً ما","partOfSpeech":"Adverb"},{"category":"Some-","learnable":"irgendwo","normalized":"irgendwo","translation":"مكان ما","partOfSpeech":"Adverb"},{"category":"Spiritual","learnable":"glücklich","normalized":"glucklich","translation":"سعيد, سعداء, سعداءً, سعيدًا, محظوظ","partOfSpeech":"Adjective"},{"category":"Spiritual","learnable":"wunderbar","normalized":"wunderbar","translation":"رائع, رائعة","partOfSpeech":"Adjective"},{"category":"Spiritual","learnable":"wunderschön","normalized":"wunderschon","translation":"رائعة, رائع","partOfSpeech":"Adjective"},{"category":"Stuff","learnable":"zeug","normalized":"zeug","translation":null,"partOfSpeech":"Neuter Noun"},{"category":"The-World","learnable":"australien","normalized":"australien","translation":null,"partOfSpeech":"Neuter Proper noun"},{"category":"The-World","learnable":"europäisch","normalized":"europaisch","translation":"أوربية, أوربى, أوروبي","partOfSpeech":"Adjective"},{"category":"Time","learnable":"damals","normalized":"damals","translation":"في ذاك الوقت","partOfSpeech":"Adverb"},{"category":"Time","learnable":"dann","normalized":"dann","translation":"بعد ذلك, إذاً, حينها, عندئذٍ","partOfSpeech":"Adverb"},{"category":"Time","learnable":"etwa","normalized":"etwa","translation":"قرابة, حوالى","partOfSpeech":"Adverb"},{"category":"Time","learnable":"fast","normalized":"fast","translation":"بالكاد","partOfSpeech":"Adverb"},{"category":"Time","learnable":"früh","normalized":"fruh","translation":"مبكرًا","partOfSpeech":"Adjective"},{"category":"Time","learnable":"gerade","normalized":"gerade","translation":"للتو, بالضبط, بالظبط, تماماً","partOfSpeech":"Adverb"},{"category":"Time","learnable":"gestern","normalized":"gestern","translation":"بالأمس, البارحة, أمس","partOfSpeech":"Adverb"},{"category":"Time","learnable":"halb","normalized":"halb","translation":"نصف","partOfSpeech":"Adjective"},{"category":"Time","learnable":"heute","normalized":"heute","translation":"اليوم","partOfSpeech":"Adverb"},{"category":"Time","learnable":"jetzt","normalized":"jetzt","translation":"الآن","partOfSpeech":"Adverb"},{"category":"Time","learnable":"morgen","normalized":"morgen","translation":"الغد, بالغد, غداً","partOfSpeech":"Adverb"},{"category":"Time","learnable":"nachts","normalized":"nachts","translation":"ليلًا, ليلا, فى الليل","partOfSpeech":"Adverb"},{"category":"Time","learnable":"sofort","normalized":"sofort","translation":"فوراً, فى الحال, حالاً","partOfSpeech":"Adverb"},{"category":"Time","learnable":"spät","normalized":"spat","translation":"متأخر, متأخرًا, متأخرة","partOfSpeech":"Adjective"},{"category":"Time","learnable":"später","normalized":"spater","translation":"لاحقًا, بعد ذلك","partOfSpeech":"Adjective"},{"category":"Time","learnable":"viertel","normalized":"viertel","translation":"ربع","partOfSpeech":"Verb"},{"category":"Verbs:-Conditional","learnable":"falls","normalized":"falls","translation":null,"partOfSpeech":"Conjunction"},{"category":"Verbs:-Conditional-2","learnable":"vorsichtig","normalized":"vorsichtig","translation":"حذرًا, حذر, حذرا, حذراً","partOfSpeech":"Adjective"},{"category":"Verbs:-Modal","learnable":"man","normalized":"man","translation":"المرء","partOfSpeech":"Determiner"},{"category":"Verbs:-Past-Perfect","learnable":"nachdem","normalized":"nachdem","translation":null,"partOfSpeech":"Conjunction"},{"category":"Verbs:-Perfect-1","learnable":"geschehen","normalized":"geschehen","translation":"حدث, حصل","partOfSpeech":"Verb"},{"category":"Verbs:-Perfect-2","learnable":"passiert","normalized":"passiert","translation":"(هو) يحدث, حدث, يحصل","partOfSpeech":"Adjective"},{"category":"Verbs:-Present-2","learnable":"gehen","normalized":"gehen","translation":"تذهب, (نحن) نذهب, أذهب, (هم) يذهبون, تذهبوا, سنذهب, يذهبان","partOfSpeech":"Verb"},{"category":"Verbs:-Present-2","learnable":"scheint","normalized":"scheint","translation":"تشرق, تبدو, يبدو","partOfSpeech":"Verb"},{"category":"Verbs:-Present-2","learnable":"schwimmen","normalized":"schwimmen","translation":"(نحن) نسبح, للسباحة, السباحة, (هم) يسبحون","partOfSpeech":"Verb"},{"category":"Verbs:-Present-3","learnable":"lernen","normalized":"lernen","translation":"أتعلم, تتعلم, (هم) يتعلمون","partOfSpeech":"Verb"},{"category":"Verbs:-Present-4","learnable":"telefonieren","normalized":"telefonieren","translation":"نتصل, تتصل, يتصل, (نحن) نتصل, (هم) يتصلون","partOfSpeech":"Verb"},{"category":"Verbs:-Present-4","learnable":"tun","normalized":"tun","translation":"أفعل, فعل, القيام","partOfSpeech":"Verb"},{"category":"Verbs:-Preterite","learnable":"bevor","normalized":"bevor","translation":"قبل أن","partOfSpeech":"Conjunction"},{"category":"Verbs:-Preterite","learnable":"vorher","normalized":"vorher","translation":"قبل ذلك","partOfSpeech":"Adverb"},{"category":"Verbs:-Preterite","learnable":"zuvor","normalized":"zuvor","translation":"من قبل, قبل ذلك","partOfSpeech":"Adverb"},{"category":"Weather","learnable":"nass","normalized":"nass","translation":"مبتل, مبتلة","partOfSpeech":"Adjective"},{"category":"Weather","learnable":"regnet","normalized":"regnet","translation":"تمطر","partOfSpeech":"Verb"},{"category":"Weather","learnable":"schneit","normalized":"schneit","translation":"(هى) تُثلج","partOfSpeech":"Verb"},{"category":"Weather","learnable":"trocken","normalized":"trocken","translation":"جاف","partOfSpeech":"Adjective"},{"category":"questions-1","learnable":"alt","normalized":"alt","translation":"قديمة, قديم, عجوز, القديمة, عجوزة, عجوزه, قدماء, كبير, كبير سناً, كبير في السن","partOfSpeech":"Adjective"},{"category":"questions-1","learnable":"jung","normalized":"jung","translation":"صغير, صغير في السن, صغيرة, حديث, حديثة, شاباً, شابة, صغار, صغار في السن, صغيرة في السن","partOfSpeech":"Adjective"},{"category":"questions-1","learnable":"kalt","normalized":"kalt","translation":"بارد, باردة, باردًا","partOfSpeech":"Adjective"},{"category":"questions-1","learnable":"langsam","normalized":"langsam","translation":"ببطء, بطيئة, بطيء, بطيئاً, بطيئون","partOfSpeech":"Adjective"},{"category":"questions-1","learnable":"neu","normalized":"neu","translation":"جديد, جديدة, الجديد, جدد, جديداً, جديدًا, حديث","partOfSpeech":"Adjective"},{"category":"questions-1","learnable":"richtig","normalized":"richtig","translation":"صحيح, صحيحة, بشكل صحيح, حقًا, صحيحاً","partOfSpeech":"Adjective"},{"category":"questions-1","learnable":"sauber","normalized":"sauber","translation":"نظيف, نظيفة, نظيفون, نظيفاً","partOfSpeech":"Adjective"},{"category":"questions-1","learnable":"schmutzig","normalized":"schmutzig","translation":"متسخ, متسخة, قذر, قذرة, وسخ","partOfSpeech":"Adjective"},{"category":"questions-1","learnable":"schnell","normalized":"schnell","translation":"سريع, بسرعة, سريعة, سريعاً, سريعون","partOfSpeech":"Adjective"},{"category":"questions-1","learnable":"schön","normalized":"schon","translation":"بالفعل, قد","partOfSpeech":"Adjective"},{"category":"questions-1","learnable":"schwer","normalized":"schwer","translation":"ثقيل, ثقيلة, صعبة, صعب","partOfSpeech":"Adjective"},{"category":"questions-1","learnable":"teuer","normalized":"teuer","translation":"غالي, غالٍ, غالية, غالى, غاليًا, مكلف","partOfSpeech":"Adjective"},{"category":"questions-1","learnable":"tief","normalized":"tief","translation":"عميق, بعمق, عميقاً","partOfSpeech":"Adjective"},{"category":"questions-1","learnable":"warm","normalized":"warm","translation":"دافئ, دافئة","partOfSpeech":"Adjective"},{"category":"questions-1","learnable":"weit","normalized":"weit","translation":"بعيد, بعيدًا, واسع, عريض","partOfSpeech":"Adjective"},{"category":"questions-1","learnable":"wichtig","normalized":"wichtig","translation":"مهم, مهمة, مهمون","partOfSpeech":"Adjective"},{"category":"questions-2","learnable":"wann","normalized":"wann","translation":"متى","partOfSpeech":"Adverb"},{"category":"questions-2","learnable":"warum","normalized":"warum","translation":"لماذا, لم","partOfSpeech":"Adverb"},{"category":"questions-2","learnable":"wie","normalized":"wie","translation":"كيف, كم, مثل, كما","partOfSpeech":"Conjunction"},{"category":"questions-2","learnable":"wie viel","normalized":"wie viel","translation":"بكم, كم","partOfSpeech":null},{"category":"questions-2","learnable":"wie viele","normalized":"wie viele","translation":"كم","partOfSpeech":null},{"category":"questions-2","learnable":"wieso","normalized":"wieso","translation":"لماذا, لِمَ","partOfSpeech":"Adverb"},{"category":"questions-2","learnable":"wo","normalized":"wo","translation":"أين, حيث","partOfSpeech":"Adverb"},{"category":"questions-2","learnable":"wofür","normalized":"wofur","translation":"لما, لِمَ","partOfSpeech":"Adverb"},{"category":"questions-2","learnable":"wohin","normalized":"wohin","translation":null,"partOfSpeech":"Adverb"},{"category":"questions-2","learnable":"worüber","normalized":"woruber","translation":"الذي","partOfSpeech":"Adverb"}]